{
 "version": 1,
 "generator": "librosa-0.11.0",
 "bpm_input": 117,
 "bpm_detected": 117.5,
 "sr": 22050,
 "onsets": [
  {
   "t": 0.0464,
   "stem": 6,
   "energy": 0.0245
  },
  {
   "t": 0.1625,
   "stem": 3,
   "energy": 1.2942
  },
  {
   "t": 0.2786,
   "stem": 3,
   "energy": 4.0883
  },
  {
   "t": 0.418,
   "stem": 6,
   "energy": 2.2321
  },
  {
   "t": 0.5341,
   "stem": 6,
   "energy": 2.4566
  },
  {
   "t": 0.6734,
   "stem": 6,
   "energy": 1.1031
  },
  {
   "t": 0.7895,
   "stem": 3,
   "energy": 2.6802
  },
  {
   "t": 0.9056,
   "stem": 6,
   "energy": 2.7676
  },
  {
   "t": 1.0449,
   "stem": 3,
   "energy": 1.3248
  },
  {
   "t": 1.161,
   "stem": 3,
   "energy": 1.95
  },
  {
   "t": 1.3003,
   "stem": 6,
   "energy": 3.0552
  },
  {
   "t": 1.4164,
   "stem": 3,
   "energy": 0.8125
  },
  {
   "t": 1.5325,
   "stem": 6,
   "energy": 2.5335
  },
  {
   "t": 1.6718,
   "stem": 6,
   "energy": 1.2107
  },
  {
   "t": 1.7879,
   "stem": 6,
   "energy": 1.8987
  },
  {
   "t": 1.9273,
   "stem": 6,
   "energy": 2.2417
  },
  {
   "t": 2.0434,
   "stem": 3,
   "energy": 2.2363
  },
  {
   "t": 2.1595,
   "stem": 6,
   "energy": 2.0962
  },
  {
   "t": 2.2988,
   "stem": 3,
   "energy": 1.9113
  },
  {
   "t": 2.4149,
   "stem": 6,
   "energy": 1.5517
  },
  {
   "t": 2.531,
   "stem": 6,
   "energy": 2.5974
  },
  {
   "t": 2.6703,
   "stem": 6,
   "energy": 1.4716
  },
  {
   "t": 2.7864,
   "stem": 6,
   "energy": 2.082
  },
  {
   "t": 2.9025,
   "stem": 6,
   "energy": 2.9605
  },
  {
   "t": 3.0418,
   "stem": 6,
   "energy": 1.6707
  },
  {
   "t": 3.1579,
   "stem": 6,
   "energy": 1.2622
  },
  {
   "t": 3.2972,
   "stem": 3,
   "energy": 1.8403
  },
  {
   "t": 3.4133,
   "stem": 6,
   "energy": 1.3751
  },
  {
   "t": 3.5294,
   "stem": 6,
   "energy": 3.0101
  },
  {
   "t": 3.6688,
   "stem": 6,
   "energy": 1.3643
  },
  {
   "t": 3.7849,
   "stem": 6,
   "energy": 2.8004
  },
  {
   "t": 3.9242,
   "stem": 6,
   "energy": 1.5897
  },
  {
   "t": 4.0403,
   "stem": 6,
   "energy": 3.2566
  },
  {
   "t": 4.1796,
   "stem": 3,
   "energy": 3.3927
  },
  {
   "t": 4.2957,
   "stem": 3,
   "energy": 1.8906
  },
  {
   "t": 4.435,
   "stem": 6,
   "energy": 4.0328
  },
  {
   "t": 4.5511,
   "stem": 3,
   "energy": 10.7467
  },
  {
   "t": 4.6904,
   "stem": 6,
   "energy": 5.1603
  },
  {
   "t": 4.8065,
   "stem": 6,
   "energy": 3.493
  },
  {
   "t": 4.9459,
   "stem": 6,
   "energy": 6.3766
  },
  {
   "t": 5.0387,
   "stem": 6,
   "energy": 2.0952
  },
  {
   "t": 5.178,
   "stem": 3,
   "energy": 2.891
  },
  {
   "t": 5.2941,
   "stem": 3,
   "energy": 2.0015
  },
  {
   "t": 5.4102,
   "stem": 3,
   "energy": 1.5713
  },
  {
   "t": 5.5496,
   "stem": 3,
   "energy": 6.5126
  },
  {
   "t": 5.6889,
   "stem": 3,
   "energy": 5.3852
  },
  {
   "t": 5.805,
   "stem": 6,
   "energy": 3.0265
  },
  {
   "t": 5.9443,
   "stem": 6,
   "energy": 5.0509
  },
  {
   "t": 6.0604,
   "stem": 0,
   "energy": 31.2226
  },
  {
   "t": 6.1765,
   "stem": 3,
   "energy": 2.2128
  },
  {
   "t": 6.2926,
   "stem": 3,
   "energy": 1.8284
  },
  {
   "t": 6.4087,
   "stem": 3,
   "energy": 1.8737
  },
  {
   "t": 6.548,
   "stem": 3,
   "energy": 5.0249
  },
  {
   "t": 6.6641,
   "stem": 3,
   "energy": 5.3009
  },
  {
   "t": 6.8034,
   "stem": 6,
   "energy": 2.7916
  },
  {
   "t": 6.9428,
   "stem": 6,
   "energy": 6.0038
  },
  {
   "t": 7.0589,
   "stem": 0,
   "energy": 28.6067
  },
  {
   "t": 7.1982,
   "stem": 3,
   "energy": 8.0103
  },
  {
   "t": 7.2911,
   "stem": 0,
   "energy": 0.0031
  },
  {
   "t": 7.3375,
   "stem": 3,
   "energy": 9.7172
  },
  {
   "t": 7.4536,
   "stem": 6,
   "energy": 6.3134
  },
  {
   "t": 7.5465,
   "stem": 3,
   "energy": 3.8258
  },
  {
   "t": 7.7322,
   "stem": 0,
   "energy": 0.0599
  },
  {
   "t": 7.8019,
   "stem": 3,
   "energy": 13.2741
  },
  {
   "t": 7.9877,
   "stem": 3,
   "energy": 0.0462
  },
  {
   "t": 8.0805,
   "stem": 1,
   "energy": 2.2341
  },
  {
   "t": 8.1734,
   "stem": 6,
   "energy": 0.7595
  },
  {
   "t": 8.2895,
   "stem": 6,
   "energy": 1.6789
  },
  {
   "t": 8.4288,
   "stem": 6,
   "energy": 3.6608
  },
  {
   "t": 8.5682,
   "stem": 0,
   "energy": 60.618
  },
  {
   "t": 8.7307,
   "stem": 3,
   "energy": 0.3688
  },
  {
   "t": 8.7771,
   "stem": 6,
   "energy": 0.0351
  },
  {
   "t": 9.0093,
   "stem": 3,
   "energy": 0.1275
  },
  {
   "t": 9.0558,
   "stem": 0,
   "energy": 17.3902
  },
  {
   "t": 9.1487,
   "stem": 0,
   "energy": 40.4084
  },
  {
   "t": 9.288,
   "stem": 3,
   "energy": 0.0935
  },
  {
   "t": 9.4273,
   "stem": 0,
   "energy": 0.3006
  },
  {
   "t": 9.5434,
   "stem": 3,
   "energy": 0.0699
  },
  {
   "t": 9.7292,
   "stem": 0,
   "energy": 0.0279
  },
  {
   "t": 9.7756,
   "stem": 3,
   "energy": 0.0823
  },
  {
   "t": 10.0078,
   "stem": 6,
   "energy": 0.006
  },
  {
   "t": 10.0542,
   "stem": 3,
   "energy": 41.244
  },
  {
   "t": 10.1703,
   "stem": 3,
   "energy": 15.7495
  },
  {
   "t": 10.2864,
   "stem": 3,
   "energy": 16.0148
  },
  {
   "t": 10.4258,
   "stem": 3,
   "energy": 2.4696
  },
  {
   "t": 10.5419,
   "stem": 6,
   "energy": 10.2454
  },
  {
   "t": 10.7044,
   "stem": 3,
   "energy": 0.4597
  },
  {
   "t": 10.7508,
   "stem": 6,
   "energy": 0.0743
  },
  {
   "t": 10.8205,
   "stem": 0,
   "energy": 0.8861
  },
  {
   "t": 11.0527,
   "stem": 0,
   "energy": 8.8941
  },
  {
   "t": 11.1688,
   "stem": 3,
   "energy": 3.6504
  },
  {
   "t": 11.3081,
   "stem": 0,
   "energy": 24.756
  },
  {
   "t": 11.4242,
   "stem": 3,
   "energy": 1.1334
  },
  {
   "t": 11.5171,
   "stem": 6,
   "energy": 0.0617
  },
  {
   "t": 11.7493,
   "stem": 3,
   "energy": 0.1279
  },
  {
   "t": 11.819,
   "stem": 0,
   "energy": 1.1956
  },
  {
   "t": 11.9815,
   "stem": 6,
   "energy": 0.0099
  },
  {
   "t": 12.0279,
   "stem": 3,
   "energy": 14.8948
  },
  {
   "t": 12.1673,
   "stem": 3,
   "energy": 20.1379
  },
  {
   "t": 12.2834,
   "stem": 3,
   "energy": 19.0192
  },
  {
   "t": 12.4459,
   "stem": 6,
   "energy": 10.4877
  },
  {
   "t": 12.5388,
   "stem": 3,
   "energy": 13.519
  },
  {
   "t": 12.7478,
   "stem": 3,
   "energy": 0.1329
  },
  {
   "t": 12.8174,
   "stem": 0,
   "energy": 0.8209
  },
  {
   "t": 13.0264,
   "stem": 3,
   "energy": 0.04
  },
  {
   "t": 13.0728,
   "stem": 1,
   "energy": 13.2192
  },
  {
   "t": 13.1657,
   "stem": 3,
   "energy": 19.0053
  },
  {
   "t": 13.305,
   "stem": 0,
   "energy": 20.7296
  },
  {
   "t": 13.4444,
   "stem": 3,
   "energy": 0.3909
  },
  {
   "t": 13.5372,
   "stem": 0,
   "energy": 0.0018
  },
  {
   "t": 13.7694,
   "stem": 6,
   "energy": 0.0239
  },
  {
   "t": 13.8159,
   "stem": 3,
   "energy": 17.2697
  },
  {
   "t": 14.0481,
   "stem": 3,
   "energy": 17.9257
  },
  {
   "t": 14.1642,
   "stem": 3,
   "energy": 19.7255
  },
  {
   "t": 14.2803,
   "stem": 6,
   "energy": 1.657
  },
  {
   "t": 14.3267,
   "stem": 3,
   "energy": 14.7326
  },
  {
   "t": 14.4428,
   "stem": 6,
   "energy": 7.4432
  },
  {
   "t": 14.5589,
   "stem": 0,
   "energy": 29.6911
  },
  {
   "t": 14.675,
   "stem": 6,
   "energy": 1.4066
  },
  {
   "t": 14.8143,
   "stem": 0,
   "energy": 0.6775
  },
  {
   "t": 15.0233,
   "stem": 6,
   "energy": 0.0409
  },
  {
   "t": 15.0698,
   "stem": 0,
   "energy": 87.7359
  },
  {
   "t": 15.1626,
   "stem": 3,
   "energy": 6.0835
  },
  {
   "t": 15.302,
   "stem": 0,
   "energy": 7.7926
  },
  {
   "t": 15.4877,
   "stem": 3,
   "energy": 0.1645
  },
  {
   "t": 15.5574,
   "stem": 0,
   "energy": 28.4782
  },
  {
   "t": 15.7663,
   "stem": 3,
   "energy": 0.0493
  },
  {
   "t": 16.0218,
   "stem": 3,
   "energy": 12.7398
  },
  {
   "t": 16.0682,
   "stem": 0,
   "energy": 67.7844
  },
  {
   "t": 16.1843,
   "stem": 6,
   "energy": 4.3696
  },
  {
   "t": 16.2772,
   "stem": 3,
   "energy": 21.2327
  },
  {
   "t": 16.4397,
   "stem": 6,
   "energy": 2.9328
  },
  {
   "t": 16.5326,
   "stem": 3,
   "energy": 20.1106
  },
  {
   "t": 16.7648,
   "stem": 3,
   "energy": 0.1026
  },
  {
   "t": 16.8112,
   "stem": 1,
   "energy": 5.6139
  },
  {
   "t": 17.0202,
   "stem": 3,
   "energy": 0.0432
  },
  {
   "t": 17.0667,
   "stem": 0,
   "energy": 58.4335
  },
  {
   "t": 17.1595,
   "stem": 3,
   "energy": 25.1092
  },
  {
   "t": 17.2989,
   "stem": 3,
   "energy": 4.5259
  },
  {
   "t": 17.4846,
   "stem": 1,
   "energy": 0.0
  },
  {
   "t": 17.5543,
   "stem": 0,
   "energy": 18.4319
  },
  {
   "t": 17.7633,
   "stem": 3,
   "energy": 0.0679
  },
  {
   "t": 17.8097,
   "stem": 1,
   "energy": 3.5658
  },
  {
   "t": 17.9722,
   "stem": 6,
   "energy": 0.0899
  },
  {
   "t": 18.0187,
   "stem": 0,
   "energy": 0.0035
  },
  {
   "t": 18.0651,
   "stem": 3,
   "energy": 88.2046
  },
  {
   "t": 18.2044,
   "stem": 6,
   "energy": 7.2256
  },
  {
   "t": 18.2973,
   "stem": 3,
   "energy": 17.5136
  },
  {
   "t": 18.4366,
   "stem": 6,
   "energy": 3.5209
  },
  {
   "t": 18.5295,
   "stem": 3,
   "energy": 21.4661
  },
  {
   "t": 18.7385,
   "stem": 3,
   "energy": 0.1033
  },
  {
   "t": 18.8082,
   "stem": 1,
   "energy": 4.0128
  },
  {
   "t": 19.0636,
   "stem": 0,
   "energy": 47.7486
  },
  {
   "t": 19.1565,
   "stem": 3,
   "energy": 44.6209
  },
  {
   "t": 19.2726,
   "stem": 6,
   "energy": 0.0395
  },
  {
   "t": 19.319,
   "stem": 3,
   "energy": 76.2273
  },
  {
   "t": 19.5512,
   "stem": 3,
   "energy": 8.3429
  },
  {
   "t": 19.6905,
   "stem": 3,
   "energy": 31.7885
  },
  {
   "t": 19.7834,
   "stem": 3,
   "energy": 13.0309
  },
  {
   "t": 19.9924,
   "stem": 6,
   "energy": 0.025
  },
  {
   "t": 20.062,
   "stem": 3,
   "energy": 64.0538
  },
  {
   "t": 20.2942,
   "stem": 6,
   "energy": 11.2727
  },
  {
   "t": 20.3407,
   "stem": 3,
   "energy": 27.4953
  },
  {
   "t": 20.4103,
   "stem": 3,
   "energy": 8.2715
  },
  {
   "t": 20.5032,
   "stem": 0,
   "energy": 0.3154
  },
  {
   "t": 20.5497,
   "stem": 3,
   "energy": 35.3862
  },
  {
   "t": 20.7586,
   "stem": 0,
   "energy": 0.0494
  },
  {
   "t": 20.8283,
   "stem": 3,
   "energy": 36.6265
  },
  {
   "t": 21.0141,
   "stem": 3,
   "energy": 8.9664
  },
  {
   "t": 21.0605,
   "stem": 0,
   "energy": 39.9337
  },
  {
   "t": 21.1766,
   "stem": 0,
   "energy": 0.2212
  },
  {
   "t": 21.2695,
   "stem": 6,
   "energy": 6.428
  },
  {
   "t": 21.3159,
   "stem": 0,
   "energy": 57.7963
  },
  {
   "t": 21.5481,
   "stem": 0,
   "energy": 4.6526
  },
  {
   "t": 21.8035,
   "stem": 1,
   "energy": 0.6443
  },
  {
   "t": 22.0125,
   "stem": 3,
   "energy": 19.5885
  },
  {
   "t": 22.059,
   "stem": 0,
   "energy": 31.1406
  },
  {
   "t": 22.1751,
   "stem": 6,
   "energy": 14.0235
  },
  {
   "t": 22.2912,
   "stem": 3,
   "energy": 30.7638
  },
  {
   "t": 22.3376,
   "stem": 6,
   "energy": 22.9523
  },
  {
   "t": 22.4073,
   "stem": 3,
   "energy": 15.0216
  },
  {
   "t": 22.4537,
   "stem": 6,
   "energy": 17.8061
  },
  {
   "t": 22.5466,
   "stem": 3,
   "energy": 36.4869
  },
  {
   "t": 22.7788,
   "stem": 0,
   "energy": 0.0063
  },
  {
   "t": 22.8252,
   "stem": 3,
   "energy": 30.351
  },
  {
   "t": 23.011,
   "stem": 6,
   "energy": 11.0666
  },
  {
   "t": 23.0574,
   "stem": 0,
   "energy": 18.925
  },
  {
   "t": 23.1735,
   "stem": 0,
   "energy": 0.5194
  },
  {
   "t": 23.22,
   "stem": 6,
   "energy": 13.672
  },
  {
   "t": 23.2896,
   "stem": 3,
   "energy": 11.4433
  },
  {
   "t": 23.5218,
   "stem": 3,
   "energy": 12.0747
  },
  {
   "t": 23.7772,
   "stem": 6,
   "energy": 7.9214
  },
  {
   "t": 24.0559,
   "stem": 0,
   "energy": 19.7939
  },
  {
   "t": 24.1952,
   "stem": 0,
   "energy": 0.1275
  },
  {
   "t": 24.2881,
   "stem": 3,
   "energy": 29.2732
  },
  {
   "t": 24.4042,
   "stem": 3,
   "energy": 10.1174
  },
  {
   "t": 24.4506,
   "stem": 6,
   "energy": 11.2269
  },
  {
   "t": 24.5435,
   "stem": 3,
   "energy": 29.3953
  },
  {
   "t": 24.7525,
   "stem": 3,
   "energy": 10.7761
  },
  {
   "t": 24.8221,
   "stem": 1,
   "energy": 11.4055
  },
  {
   "t": 24.9847,
   "stem": 3,
   "energy": 8.2186
  },
  {
   "t": 25.0543,
   "stem": 0,
   "energy": 12.5584
  },
  {
   "t": 25.1937,
   "stem": 0,
   "energy": 0.3221
  },
  {
   "t": 25.2633,
   "stem": 6,
   "energy": 8.7023
  },
  {
   "t": 25.5187,
   "stem": 3,
   "energy": 0.4509
  },
  {
   "t": 25.5652,
   "stem": 1,
   "energy": 7.1012
  },
  {
   "t": 25.7741,
   "stem": 3,
   "energy": 0.5892
  },
  {
   "t": 25.8206,
   "stem": 1,
   "energy": 7.9886
  },
  {
   "t": 26.0296,
   "stem": 3,
   "energy": 20.5833
  },
  {
   "t": 26.1689,
   "stem": 6,
   "energy": 11.6447
  },
  {
   "t": 26.3082,
   "stem": 3,
   "energy": 31.6185
  },
  {
   "t": 26.4475,
   "stem": 6,
   "energy": 12.2822
  },
  {
   "t": 26.5404,
   "stem": 3,
   "energy": 24.0436
  },
  {
   "t": 26.819,
   "stem": 3,
   "energy": 18.5737
  },
  {
   "t": 27.028,
   "stem": 3,
   "energy": 10.5967
  },
  {
   "t": 27.1673,
   "stem": 3,
   "energy": 24.0299
  },
  {
   "t": 27.3067,
   "stem": 3,
   "energy": 35.3641
  },
  {
   "t": 27.4228,
   "stem": 3,
   "energy": 11.3694
  },
  {
   "t": 27.5621,
   "stem": 6,
   "energy": 12.4751
  },
  {
   "t": 27.7014,
   "stem": 3,
   "energy": 26.7294
  },
  {
   "t": 27.8175,
   "stem": 6,
   "energy": 10.3275
  },
  {
   "t": 28.0265,
   "stem": 3,
   "energy": 18.1539
  },
  {
   "t": 28.2819,
   "stem": 3,
   "energy": 27.4524
  },
  {
   "t": 28.4444,
   "stem": 1,
   "energy": 13.1217
  },
  {
   "t": 28.5373,
   "stem": 3,
   "energy": 30.3408
  },
  {
   "t": 28.7695,
   "stem": 0,
   "energy": 0.0122
  },
  {
   "t": 28.816,
   "stem": 3,
   "energy": 22.1069
  },
  {
   "t": 29.0482,
   "stem": 3,
   "energy": 15.2672
  },
  {
   "t": 29.1643,
   "stem": 3,
   "energy": 27.3157
  },
  {
   "t": 29.2107,
   "stem": 6,
   "energy": 9.4542
  },
  {
   "t": 29.3036,
   "stem": 0,
   "energy": 13.7872
  },
  {
   "t": 29.5126,
   "stem": 3,
   "energy": 0.2912
  },
  {
   "t": 29.559,
   "stem": 1,
   "energy": 4.5624
  },
  {
   "t": 29.6519,
   "stem": 6,
   "energy": 11.2611
  },
  {
   "t": 29.768,
   "stem": 3,
   "energy": 0.5198
  },
  {
   "t": 29.8144,
   "stem": 1,
   "energy": 6.3944
  },
  {
   "t": 30.0234,
   "stem": 3,
   "energy": 19.2712
  },
  {
   "t": 30.0698,
   "stem": 0,
   "energy": 65.4927
  },
  {
   "t": 30.1627,
   "stem": 6,
   "energy": 14.3843
  },
  {
   "t": 30.3253,
   "stem": 3,
   "energy": 34.0607
  },
  {
   "t": 30.4414,
   "stem": 6,
   "energy": 14.8164
  },
  {
   "t": 30.5575,
   "stem": 3,
   "energy": 61.2521
  },
  {
   "t": 30.8129,
   "stem": 3,
   "energy": 22.5492
  },
  {
   "t": 31.0219,
   "stem": 6,
   "energy": 10.8446
  },
  {
   "t": 31.0683,
   "stem": 0,
   "energy": 58.7231
  },
  {
   "t": 31.1612,
   "stem": 3,
   "energy": 29.3554
  },
  {
   "t": 31.2076,
   "stem": 6,
   "energy": 10.7122
  },
  {
   "t": 31.2773,
   "stem": 3,
   "energy": 8.0851
  },
  {
   "t": 31.5559,
   "stem": 3,
   "energy": 38.4173
  },
  {
   "t": 31.7417,
   "stem": 3,
   "energy": 7.5466
  },
  {
   "t": 31.8113,
   "stem": 1,
   "energy": 3.9988
  },
  {
   "t": 32.0203,
   "stem": 3,
   "energy": 20.7713
  },
  {
   "t": 32.1829,
   "stem": 0,
   "energy": 0.4878
  },
  {
   "t": 32.299,
   "stem": 3,
   "energy": 32.0819
  },
  {
   "t": 32.3918,
   "stem": 6,
   "energy": 13.126
  },
  {
   "t": 32.5544,
   "stem": 3,
   "energy": 54.6678
  },
  {
   "t": 32.7634,
   "stem": 6,
   "energy": 6.4741
  },
  {
   "t": 32.8098,
   "stem": 1,
   "energy": 6.7846
  },
  {
   "t": 33.0188,
   "stem": 6,
   "energy": 10.6684
  },
  {
   "t": 33.0652,
   "stem": 0,
   "energy": 45.5854
  },
  {
   "t": 33.1581,
   "stem": 3,
   "energy": 46.3061
  },
  {
   "t": 33.2974,
   "stem": 3,
   "energy": 8.3788
  },
  {
   "t": 33.5528,
   "stem": 0,
   "energy": 13.6258
  },
  {
   "t": 33.8083,
   "stem": 1,
   "energy": 2.5738
  },
  {
   "t": 34.0405,
   "stem": 3,
   "energy": 18.3364
  },
  {
   "t": 34.1798,
   "stem": 0,
   "energy": 0.3189
  },
  {
   "t": 34.2959,
   "stem": 3,
   "energy": 32.8944
  },
  {
   "t": 34.4352,
   "stem": 3,
   "energy": 18.2643
  },
  {
   "t": 34.5513,
   "stem": 3,
   "energy": 36.6775
  },
  {
   "t": 34.7371,
   "stem": 3,
   "energy": 10.9224
  },
  {
   "t": 34.8067,
   "stem": 1,
   "energy": 2.0762
  },
  {
   "t": 35.0157,
   "stem": 3,
   "energy": 9.8615
  },
  {
   "t": 35.0621,
   "stem": 0,
   "energy": 26.0619
  },
  {
   "t": 35.1782,
   "stem": 0,
   "energy": 0.4752
  },
  {
   "t": 35.2711,
   "stem": 6,
   "energy": 12.0528
  },
  {
   "t": 35.5265,
   "stem": 3,
   "energy": 13.4663
  },
  {
   "t": 35.7587,
   "stem": 3,
   "energy": 0.626
  },
  {
   "t": 35.8052,
   "stem": 1,
   "energy": 4.6719
  },
  {
   "t": 35.9213,
   "stem": 6,
   "energy": 10.5703
  },
  {
   "t": 36.0606,
   "stem": 0,
   "energy": 34.7097
  },
  {
   "t": 36.1767,
   "stem": 3,
   "energy": 26.7343
  },
  {
   "t": 36.2928,
   "stem": 3,
   "energy": 28.1362
  },
  {
   "t": 36.4089,
   "stem": 3,
   "energy": 9.1048
  },
  {
   "t": 36.4553,
   "stem": 6,
   "energy": 10.1222
  },
  {
   "t": 36.525,
   "stem": 3,
   "energy": 26.0061
  },
  {
   "t": 36.7572,
   "stem": 3,
   "energy": 12.6815
  },
  {
   "t": 36.8036,
   "stem": 1,
   "energy": 0.8656
  },
  {
   "t": 36.9894,
   "stem": 3,
   "energy": 23.911
  },
  {
   "t": 37.0823,
   "stem": 1,
   "energy": 12.3299
  },
  {
   "t": 37.1751,
   "stem": 0,
   "energy": 0.5562
  },
  {
   "t": 37.3145,
   "stem": 3,
   "energy": 85.771
  },
  {
   "t": 37.4306,
   "stem": 1,
   "energy": 2.6752
  },
  {
   "t": 37.5467,
   "stem": 3,
   "energy": 32.5219
  },
  {
   "t": 37.7556,
   "stem": 3,
   "energy": 0.7713
  },
  {
   "t": 37.8021,
   "stem": 1,
   "energy": 1.3599
  },
  {
   "t": 38.0111,
   "stem": 3,
   "energy": 14.6441
  },
  {
   "t": 38.0575,
   "stem": 0,
   "energy": 18.667
  },
  {
   "t": 38.2665,
   "stem": 6,
   "energy": 16.7514
  },
  {
   "t": 38.3129,
   "stem": 3,
   "energy": 29.3805
  },
  {
   "t": 38.429,
   "stem": 3,
   "energy": 18.11
  },
  {
   "t": 38.5451,
   "stem": 3,
   "energy": 32.0135
  },
  {
   "t": 38.8005,
   "stem": 3,
   "energy": 20.2611
  },
  {
   "t": 39.056,
   "stem": 0,
   "energy": 33.5533
  },
  {
   "t": 39.1953,
   "stem": 3,
   "energy": 54.2637
  },
  {
   "t": 39.3114,
   "stem": 6,
   "energy": 11.4629
  },
  {
   "t": 39.4507,
   "stem": 6,
   "energy": 13.8186
  },
  {
   "t": 39.5436,
   "stem": 3,
   "energy": 13.0653
  },
  {
   "t": 39.6597,
   "stem": 6,
   "energy": 10.5798
  },
  {
   "t": 39.7758,
   "stem": 3,
   "energy": 28.2581
  },
  {
   "t": 39.8919,
   "stem": 6,
   "energy": 7.773
  },
  {
   "t": 39.9383,
   "stem": 3,
   "energy": 71.7288
  },
  {
   "t": 40.0312,
   "stem": 6,
   "energy": 1.7866
  },
  {
   "t": 40.0776,
   "stem": 3,
   "energy": 114.3759
  },
  {
   "t": 40.2866,
   "stem": 0,
   "energy": 0.3003
  },
  {
   "t": 40.5188,
   "stem": 3,
   "energy": 18.3961
  },
  {
   "t": 40.7278,
   "stem": 0,
   "energy": 0.0375
  },
  {
   "t": 40.9368,
   "stem": 1,
   "energy": 5.2118
  },
  {
   "t": 41.0761,
   "stem": 3,
   "energy": 115.6849
  },
  {
   "t": 41.1922,
   "stem": 0,
   "energy": 0.3626
  },
  {
   "t": 41.3083,
   "stem": 3,
   "energy": 71.3394
  },
  {
   "t": 41.5173,
   "stem": 3,
   "energy": 13.7302
  },
  {
   "t": 41.5637,
   "stem": 1,
   "energy": 6.0612
  },
  {
   "t": 41.8191,
   "stem": 3,
   "energy": 47.4958
  },
  {
   "t": 42.0281,
   "stem": 3,
   "energy": 35.0275
  },
  {
   "t": 42.3068,
   "stem": 0,
   "energy": 0.6257
  },
  {
   "t": 42.539,
   "stem": 3,
   "energy": 18.2094
  },
  {
   "t": 42.7712,
   "stem": 0,
   "energy": 0.0036
  },
  {
   "t": 42.8176,
   "stem": 3,
   "energy": 40.4627
  },
  {
   "t": 43.073,
   "stem": 3,
   "energy": 119.1883
  },
  {
   "t": 43.1891,
   "stem": 0,
   "energy": 0.2789
  },
  {
   "t": 43.3284,
   "stem": 3,
   "energy": 121.3008
  },
  {
   "t": 43.491,
   "stem": 3,
   "energy": 15.4803
  },
  {
   "t": 43.5374,
   "stem": 0,
   "energy": 0.0104
  },
  {
   "t": 43.7232,
   "stem": 3,
   "energy": 36.4368
  },
  {
   "t": 43.8161,
   "stem": 0,
   "energy": 0.9532
  },
  {
   "t": 44.025,
   "stem": 0,
   "energy": 0.0009
  },
  {
   "t": 44.0715,
   "stem": 3,
   "energy": 122.5191
  },
  {
   "t": 44.2805,
   "stem": 3,
   "energy": 40.1235
  },
  {
   "t": 44.5359,
   "stem": 3,
   "energy": 19.7141
  },
  {
   "t": 44.6288,
   "stem": 6,
   "energy": 22.0227
  },
  {
   "t": 44.8145,
   "stem": 3,
   "energy": 40.0157
  },
  {
   "t": 45.0235,
   "stem": 3,
   "energy": 41.7204
  },
  {
   "t": 45.186,
   "stem": 0,
   "energy": 0.4107
  },
  {
   "t": 45.3254,
   "stem": 3,
   "energy": 109.8067
  },
  {
   "t": 45.5576,
   "stem": 3,
   "energy": 41.0657
  },
  {
   "t": 45.7898,
   "stem": 0,
   "energy": 0.0071
  },
  {
   "t": 45.9987,
   "stem": 3,
   "energy": 41.0501
  },
  {
   "t": 46.0916,
   "stem": 6,
   "energy": 16.5193
  },
  {
   "t": 46.2541,
   "stem": 0,
   "energy": 0.0064
  },
  {
   "t": 46.5096,
   "stem": 0,
   "energy": 0.0003
  },
  {
   "t": 46.556,
   "stem": 3,
   "energy": 59.6012
  },
  {
   "t": 46.8114,
   "stem": 3,
   "energy": 51.6894
  },
  {
   "t": 47.0668,
   "stem": 3,
   "energy": 101.2937
  },
  {
   "t": 47.1829,
   "stem": 0,
   "energy": 0.4623
  },
  {
   "t": 47.3223,
   "stem": 3,
   "energy": 95.4091
  },
  {
   "t": 47.4848,
   "stem": 0,
   "energy": 0.0138
  },
  {
   "t": 47.5777,
   "stem": 3,
   "energy": 91.7461
  },
  {
   "t": 47.7634,
   "stem": 3,
   "energy": 38.3601
  },
  {
   "t": 48.0189,
   "stem": 3,
   "energy": 23.9847
  },
  {
   "t": 48.0653,
   "stem": 0,
   "energy": 56.0617
  },
  {
   "t": 48.2975,
   "stem": 0,
   "energy": 0.4527
  },
  {
   "t": 48.5529,
   "stem": 3,
   "energy": 43.0564
  },
  {
   "t": 48.8083,
   "stem": 0,
   "energy": 0.6167
  },
  {
   "t": 48.9477,
   "stem": 1,
   "energy": 9.9768
  },
  {
   "t": 49.0638,
   "stem": 3,
   "energy": 88.2056
  },
  {
   "t": 49.1799,
   "stem": 0,
   "energy": 0.6129
  },
  {
   "t": 49.3192,
   "stem": 3,
   "energy": 105.4855
  },
  {
   "t": 49.5746,
   "stem": 3,
   "energy": 96.1648
  },
  {
   "t": 49.7604,
   "stem": 0,
   "energy": 0.007
  },
  {
   "t": 49.8068,
   "stem": 1,
   "energy": 15.7427
  },
  {
   "t": 50.0622,
   "stem": 0,
   "energy": 37.7759
  },
  {
   "t": 50.2944,
   "stem": 0,
   "energy": 0.0074
  },
  {
   "t": 50.5498,
   "stem": 3,
   "energy": 30.1884
  },
  {
   "t": 50.8053,
   "stem": 0,
   "energy": 0.3573
  },
  {
   "t": 51.0839,
   "stem": 3,
   "energy": 141.0139
  },
  {
   "t": 51.1768,
   "stem": 0,
   "energy": 0.2994
  },
  {
   "t": 51.3161,
   "stem": 3,
   "energy": 83.7977
  },
  {
   "t": 51.5019,
   "stem": 1,
   "energy": 0.0001
  },
  {
   "t": 51.5715,
   "stem": 3,
   "energy": 77.0879
  },
  {
   "t": 51.8037,
   "stem": 0,
   "energy": 0.3816
  },
  {
   "t": 52.0127,
   "stem": 3,
   "energy": 30.4058
  },
  {
   "t": 52.0591,
   "stem": 0,
   "energy": 31.7008
  },
  {
   "t": 52.3146,
   "stem": 3,
   "energy": 31.0562
  },
  {
   "t": 52.5468,
   "stem": 3,
   "energy": 16.58
  },
  {
   "t": 52.779,
   "stem": 0,
   "energy": 0.0046
  },
  {
   "t": 53.0808,
   "stem": 3,
   "energy": 107.3448
  },
  {
   "t": 53.1737,
   "stem": 0,
   "energy": 0.2667
  },
  {
   "t": 53.2898,
   "stem": 3,
   "energy": 26.6096
  },
  {
   "t": 53.4291,
   "stem": 0,
   "energy": 0.3526
  },
  {
   "t": 53.5452,
   "stem": 3,
   "energy": 9.6707
  },
  {
   "t": 53.8239,
   "stem": 3,
   "energy": 30.28
  },
  {
   "t": 54.0793,
   "stem": 3,
   "energy": 98.854
  },
  {
   "t": 54.3115,
   "stem": 3,
   "energy": 30.1582
  },
  {
   "t": 54.5437,
   "stem": 3,
   "energy": 14.1736
  },
  {
   "t": 54.7991,
   "stem": 0,
   "energy": 0.2106
  },
  {
   "t": 54.892,
   "stem": 1,
   "energy": 0.0046
  },
  {
   "t": 55.0777,
   "stem": 3,
   "energy": 101.3311
  },
  {
   "t": 55.1706,
   "stem": 0,
   "energy": 0.3827
  },
  {
   "t": 55.3099,
   "stem": 0,
   "energy": 32.3324
  },
  {
   "t": 55.4957,
   "stem": 3,
   "energy": 12.3013
  },
  {
   "t": 55.5421,
   "stem": 0,
   "energy": 0.0167
  },
  {
   "t": 55.7511,
   "stem": 3,
   "energy": 26.0742
  },
  {
   "t": 55.8208,
   "stem": 0,
   "energy": 1.1661
  },
  {
   "t": 56.0298,
   "stem": 0,
   "energy": 0.0145
  },
  {
   "t": 56.0762,
   "stem": 3,
   "energy": 129.1637
  },
  {
   "t": 56.1691,
   "stem": 3,
   "energy": 18.4025
  },
  {
   "t": 56.3084,
   "stem": 3,
   "energy": 19.4407
  },
  {
   "t": 56.4477,
   "stem": 1,
   "energy": 9.9889
  },
  {
   "t": 56.5406,
   "stem": 3,
   "energy": 18.0001
  },
  {
   "t": 56.6567,
   "stem": 6,
   "energy": 1.6877
  },
  {
   "t": 56.796,
   "stem": 3,
   "energy": 1.4171
  },
  {
   "t": 56.9121,
   "stem": 3,
   "energy": 15.3708
  },
  {
   "t": 57.0514,
   "stem": 0,
   "energy": 4.9283
  },
  {
   "t": 57.1675,
   "stem": 3,
   "energy": 14.1815
  },
  {
   "t": 57.3068,
   "stem": 0,
   "energy": 19.5445
  },
  {
   "t": 57.4462,
   "stem": 3,
   "energy": 6.6338
  },
  {
   "t": 57.539,
   "stem": 3,
   "energy": 3.42
  },
  {
   "t": 57.6784,
   "stem": 6,
   "energy": 1.7275
  },
  {
   "t": 57.8177,
   "stem": 1,
   "energy": 6.4404
  },
  {
   "t": 57.9106,
   "stem": 6,
   "energy": 1.6546
  },
  {
   "t": 58.0267,
   "stem": 3,
   "energy": 23.9885
  },
  {
   "t": 58.166,
   "stem": 3,
   "energy": 19.8171
  },
  {
   "t": 58.2821,
   "stem": 3,
   "energy": 21.0143
  },
  {
   "t": 58.4446,
   "stem": 1,
   "energy": 9.4745
  },
  {
   "t": 58.4911,
   "stem": 0,
   "energy": 0.0001
  },
  {
   "t": 58.5375,
   "stem": 3,
   "energy": 22.2383
  },
  {
   "t": 58.6536,
   "stem": 6,
   "energy": 2.2034
  },
  {
   "t": 58.7929,
   "stem": 3,
   "energy": 2.6067
  },
  {
   "t": 58.909,
   "stem": 6,
   "energy": 1.7436
  },
  {
   "t": 59.0483,
   "stem": 3,
   "energy": 10.9623
  },
  {
   "t": 59.1877,
   "stem": 3,
   "energy": 60.5189
  },
  {
   "t": 59.327,
   "stem": 3,
   "energy": 111.9802
  },
  {
   "t": 59.4199,
   "stem": 6,
   "energy": 1.1898
  },
  {
   "t": 59.5592,
   "stem": 0,
   "energy": 35.2711
  },
  {
   "t": 59.6985,
   "stem": 3,
   "energy": 33.9796
  },
  {
   "t": 59.7682,
   "stem": 1,
   "energy": 11.2554
  },
  {
   "t": 59.9075,
   "stem": 6,
   "energy": 2.0985
  },
  {
   "t": 59.9771,
   "stem": 0,
   "energy": 2.6994
  },
  {
   "t": 60.0468,
   "stem": 3,
   "energy": 21.7033
  },
  {
   "t": 60.3951,
   "stem": 6,
   "energy": 11.7212
  },
  {
   "t": 60.4415,
   "stem": 1,
   "energy": 8.8305
  },
  {
   "t": 60.5576,
   "stem": 3,
   "energy": 52.6366
  },
  {
   "t": 60.7434,
   "stem": 0,
   "energy": 0.0594
  },
  {
   "t": 60.8131,
   "stem": 3,
   "energy": 21.3893
  },
  {
   "t": 61.022,
   "stem": 3,
   "energy": 10.9498
  },
  {
   "t": 61.0685,
   "stem": 0,
   "energy": 74.6424
  },
  {
   "t": 61.1614,
   "stem": 3,
   "energy": 37.5418
  },
  {
   "t": 61.2775,
   "stem": 6,
   "energy": 7.7279
  },
  {
   "t": 61.5097,
   "stem": 6,
   "energy": 0.4139
  },
  {
   "t": 61.5561,
   "stem": 0,
   "energy": 26.6401
  },
  {
   "t": 61.6722,
   "stem": 6,
   "energy": 10.5601
  },
  {
   "t": 61.7651,
   "stem": 3,
   "energy": 0.2745
  },
  {
   "t": 61.8115,
   "stem": 1,
   "energy": 3.7385
  },
  {
   "t": 62.0205,
   "stem": 3,
   "energy": 15.8849
  },
  {
   "t": 62.0669,
   "stem": 0,
   "energy": 70.4158
  },
  {
   "t": 62.1598,
   "stem": 6,
   "energy": 15.9912
  },
  {
   "t": 62.3224,
   "stem": 3,
   "energy": 32.2892
  },
  {
   "t": 62.4385,
   "stem": 6,
   "energy": 12.3288
  },
  {
   "t": 62.5313,
   "stem": 3,
   "energy": 26.1475
  },
  {
   "t": 62.7635,
   "stem": 0,
   "energy": 0.0066
  },
  {
   "t": 62.81,
   "stem": 3,
   "energy": 20.0481
  },
  {
   "t": 63.019,
   "stem": 3,
   "energy": 9.4594
  },
  {
   "t": 63.0654,
   "stem": 0,
   "energy": 58.818
  },
  {
   "t": 63.1815,
   "stem": 3,
   "energy": 27.3361
  },
  {
   "t": 63.2744,
   "stem": 3,
   "energy": 11.4988
  },
  {
   "t": 63.553,
   "stem": 0,
   "energy": 16.7598
  },
  {
   "t": 63.7852,
   "stem": 6,
   "energy": 9.5514
  },
  {
   "t": 64.0406,
   "stem": 3,
   "energy": 18.5894
  },
  {
   "t": 64.3193,
   "stem": 3,
   "energy": 31.1009
  },
  {
   "t": 64.4354,
   "stem": 3,
   "energy": 18.4478
  },
  {
   "t": 64.5515,
   "stem": 3,
   "energy": 45.9629
  },
  {
   "t": 64.8069,
   "stem": 3,
   "energy": 17.9591
  },
  {
   "t": 64.9927,
   "stem": 3,
   "energy": 8.9866
  },
  {
   "t": 65.0623,
   "stem": 0,
   "energy": 35.0427
  },
  {
   "t": 65.1784,
   "stem": 0,
   "energy": 0.5051
  },
  {
   "t": 65.2713,
   "stem": 3,
   "energy": 10.0857
  },
  {
   "t": 65.3177,
   "stem": 0,
   "energy": 60.7302
  },
  {
   "t": 65.5499,
   "stem": 0,
   "energy": 5.3911
  },
  {
   "t": 65.7589,
   "stem": 3,
   "energy": 1.0338
  },
  {
   "t": 65.8054,
   "stem": 1,
   "energy": 1.8824
  },
  {
   "t": 66.0376,
   "stem": 3,
   "energy": 22.1009
  },
  {
   "t": 66.3162,
   "stem": 3,
   "energy": 33.2462
  },
  {
   "t": 66.4091,
   "stem": 3,
   "energy": 14.7017
  },
  {
   "t": 66.4555,
   "stem": 6,
   "energy": 19.6515
  },
  {
   "t": 66.5484,
   "stem": 3,
   "energy": 30.2766
  },
  {
   "t": 66.827,
   "stem": 3,
   "energy": 29.5534
  },
  {
   "t": 67.0592,
   "stem": 0,
   "energy": 23.2971
  },
  {
   "t": 67.1753,
   "stem": 0,
   "energy": 0.5486
  },
  {
   "t": 67.3146,
   "stem": 0,
   "energy": 53.7664
  },
  {
   "t": 67.5004,
   "stem": 3,
   "energy": 9.3913
  },
  {
   "t": 67.5468,
   "stem": 6,
   "energy": 9.8922
  },
  {
   "t": 67.779,
   "stem": 6,
   "energy": 11.9379
  },
  {
   "t": 67.8255,
   "stem": 1,
   "energy": 12.4961
  },
  {
   "t": 68.0112,
   "stem": 3,
   "energy": 15.8985
  },
  {
   "t": 68.0577,
   "stem": 0,
   "energy": 20.3847
  },
  {
   "t": 68.3131,
   "stem": 3,
   "energy": 29.8182
  },
  {
   "t": 68.406,
   "stem": 3,
   "energy": 10.0796
  },
  {
   "t": 68.4524,
   "stem": 6,
   "energy": 8.6112
  },
  {
   "t": 68.5685,
   "stem": 3,
   "energy": 91.7905
  },
  {
   "t": 68.8239,
   "stem": 3,
   "energy": 30.3786
  },
  {
   "t": 69.0561,
   "stem": 3,
   "energy": 29.9383
  },
  {
   "t": 69.1722,
   "stem": 0,
   "energy": 0.5206
  },
  {
   "t": 69.2651,
   "stem": 6,
   "energy": 7.9018
  },
  {
   "t": 69.3116,
   "stem": 0,
   "energy": 37.0666
  },
  {
   "t": 69.5205,
   "stem": 3,
   "energy": 0.4012
  },
  {
   "t": 69.776,
   "stem": 3,
   "energy": 0.3311
  },
  {
   "t": 69.8224,
   "stem": 1,
   "energy": 6.1964
  },
  {
   "t": 70.0082,
   "stem": 3,
   "energy": 18.2909
  },
  {
   "t": 70.0546,
   "stem": 0,
   "energy": 14.5697
  },
  {
   "t": 70.1707,
   "stem": 6,
   "energy": 13.6449
  },
  {
   "t": 70.31,
   "stem": 3,
   "energy": 34.4936
  },
  {
   "t": 70.4493,
   "stem": 6,
   "energy": 12.9617
  },
  {
   "t": 70.5422,
   "stem": 3,
   "energy": 29.2526
  },
  {
   "t": 70.7744,
   "stem": 0,
   "energy": 0.0074
  },
  {
   "t": 70.8209,
   "stem": 3,
   "energy": 26.6551
  },
  {
   "t": 71.0298,
   "stem": 6,
   "energy": 13.702
  },
  {
   "t": 71.0763,
   "stem": 1,
   "energy": 7.8795
  },
  {
   "t": 71.1692,
   "stem": 3,
   "energy": 29.8961
  },
  {
   "t": 71.2388,
   "stem": 6,
   "energy": 11.7894
  },
  {
   "t": 71.3085,
   "stem": 0,
   "energy": 31.6634
  },
  {
   "t": 71.5407,
   "stem": 3,
   "energy": 6.5857
  },
  {
   "t": 71.7497,
   "stem": 6,
   "energy": 7.4721
  },
  {
   "t": 71.8193,
   "stem": 1,
   "energy": 7.2073
  },
  {
   "t": 72.0051,
   "stem": 6,
   "energy": 1.1021
  },
  {
   "t": 72.0515,
   "stem": 3,
   "energy": 27.4346
  },
  {
   "t": 72.1908,
   "stem": 0,
   "energy": 0.2497
  },
  {
   "t": 72.2837,
   "stem": 3,
   "energy": 29.4457
  },
  {
   "t": 72.4463,
   "stem": 6,
   "energy": 16.7736
  },
  {
   "t": 72.5624,
   "stem": 3,
   "energy": 71.5681
  },
  {
   "t": 72.7017,
   "stem": 3,
   "energy": 9.845
  },
  {
   "t": 72.7713,
   "stem": 6,
   "energy": 7.1993
  },
  {
   "t": 72.8178,
   "stem": 0,
   "energy": 0.8083
  },
  {
   "t": 73.0268,
   "stem": 6,
   "energy": 10.8446
  },
  {
   "t": 73.0732,
   "stem": 1,
   "energy": 1.5339
  },
  {
   "t": 73.1661,
   "stem": 0,
   "energy": 2.3045
  },
  {
   "t": 73.2125,
   "stem": 3,
   "energy": 19.4275
  },
  {
   "t": 73.259,
   "stem": 6,
   "energy": 8.2144
  },
  {
   "t": 73.3054,
   "stem": 0,
   "energy": 20.6426
  },
  {
   "t": 73.4679,
   "stem": 6,
   "energy": 0.4717
  },
  {
   "t": 73.5144,
   "stem": 3,
   "energy": 0.3851
  },
  {
   "t": 73.5608,
   "stem": 1,
   "energy": 1.3202
  },
  {
   "t": 73.8162,
   "stem": 1,
   "energy": 6.7144
  },
  {
   "t": 74.0252,
   "stem": 3,
   "energy": 16.9202
  },
  {
   "t": 74.1645,
   "stem": 0,
   "energy": 4.7498
  },
  {
   "t": 74.3039,
   "stem": 3,
   "energy": 33.1714
  },
  {
   "t": 74.42,
   "stem": 3,
   "energy": 11.7379
  },
  {
   "t": 74.5361,
   "stem": 3,
   "energy": 26.0067
  },
  {
   "t": 74.8147,
   "stem": 3,
   "energy": 23.6222
  },
  {
   "t": 75.0237,
   "stem": 6,
   "energy": 10.7138
  },
  {
   "t": 75.0701,
   "stem": 1,
   "energy": 1.717
  },
  {
   "t": 75.163,
   "stem": 3,
   "energy": 35.051
  },
  {
   "t": 75.2327,
   "stem": 6,
   "energy": 10.186
  },
  {
   "t": 75.2791,
   "stem": 3,
   "energy": 12.6282
  },
  {
   "t": 75.5345,
   "stem": 3,
   "energy": 12.7006
  },
  {
   "t": 75.7667,
   "stem": 3,
   "energy": 0.7298
  },
  {
   "t": 75.8132,
   "stem": 1,
   "energy": 6.9624
  },
  {
   "t": 75.906,
   "stem": 6,
   "energy": 13.4531
  },
  {
   "t": 76.0221,
   "stem": 3,
   "energy": 28.4345
  },
  {
   "t": 76.0686,
   "stem": 0,
   "energy": 62.1001
  },
  {
   "t": 76.1615,
   "stem": 6,
   "energy": 12.6918
  },
  {
   "t": 76.324,
   "stem": 3,
   "energy": 26.9607
  },
  {
   "t": 76.3937,
   "stem": 6,
   "energy": 10.3916
  },
  {
   "t": 76.4401,
   "stem": 1,
   "energy": 6.9459
  },
  {
   "t": 76.533,
   "stem": 3,
   "energy": 23.1823
  },
  {
   "t": 76.7884,
   "stem": 6,
   "energy": 12.189
  },
  {
   "t": 76.9741,
   "stem": 6,
   "energy": 10.9116
  },
  {
   "t": 77.0206,
   "stem": 3,
   "energy": 21.3599
  },
  {
   "t": 77.067,
   "stem": 0,
   "energy": 47.935
  },
  {
   "t": 77.1599,
   "stem": 3,
   "energy": 29.1407
  },
  {
   "t": 77.276,
   "stem": 3,
   "energy": 25.2962
  },
  {
   "t": 77.4153,
   "stem": 3,
   "energy": 15.4822
  },
  {
   "t": 77.5314,
   "stem": 3,
   "energy": 27.4956
  },
  {
   "t": 77.7636,
   "stem": 3,
   "energy": 0.7137
  },
  {
   "t": 77.8101,
   "stem": 1,
   "energy": 7.4483
  },
  {
   "t": 78.0423,
   "stem": 3,
   "energy": 16.5172
  },
  {
   "t": 78.2745,
   "stem": 3,
   "energy": 29.9341
  },
  {
   "t": 78.4138,
   "stem": 3,
   "energy": 10.4348
  },
  {
   "t": 78.4602,
   "stem": 6,
   "energy": 9.4545
  },
  {
   "t": 78.5299,
   "stem": 3,
   "energy": 31.377
  },
  {
   "t": 78.7853,
   "stem": 6,
   "energy": 12.271
  },
  {
   "t": 79.0407,
   "stem": 3,
   "energy": 9.5958
  },
  {
   "t": 79.2033,
   "stem": 3,
   "energy": 46.5838
  },
  {
   "t": 79.4122,
   "stem": 3,
   "energy": 14.7925
  },
  {
   "t": 79.5283,
   "stem": 3,
   "energy": 17.6102
  },
  {
   "t": 79.6677,
   "stem": 6,
   "energy": 7.6944
  },
  {
   "t": 79.7373,
   "stem": 0,
   "energy": 0.2419
  },
  {
   "t": 79.7838,
   "stem": 3,
   "energy": 26.9698
  },
  {
   "t": 79.9463,
   "stem": 3,
   "energy": 97.9243
  },
  {
   "t": 80.0624,
   "stem": 3,
   "energy": 56.3894
  },
  {
   "t": 80.3178,
   "stem": 0,
   "energy": 0.8334
  },
  {
   "t": 80.5036,
   "stem": 3,
   "energy": 17.1353
  },
  {
   "t": 80.55,
   "stem": 1,
   "energy": 0.0027
  },
  {
   "t": 80.7358,
   "stem": 0,
   "energy": 0.0244
  },
  {
   "t": 80.9215,
   "stem": 1,
   "energy": 0.0163
  },
  {
   "t": 81.0609,
   "stem": 3,
   "energy": 77.1513
  },
  {
   "t": 81.177,
   "stem": 0,
   "energy": 0.4126
  },
  {
   "t": 81.2698,
   "stem": 0,
   "energy": 0.0032
  },
  {
   "t": 81.3163,
   "stem": 3,
   "energy": 86.8781
  },
  {
   "t": 81.5717,
   "stem": 3,
   "energy": 86.4063
  },
  {
   "t": 81.7807,
   "stem": 0,
   "energy": 0.0078
  },
  {
   "t": 81.8271,
   "stem": 3,
   "energy": 40.1046
  },
  {
   "t": 81.9897,
   "stem": 3,
   "energy": 32.5195
  },
  {
   "t": 82.0593,
   "stem": 0,
   "energy": 31.8898
  },
  {
   "t": 82.3147,
   "stem": 3,
   "energy": 28.8526
  },
  {
   "t": 82.5702,
   "stem": 3,
   "energy": 77.6444
  },
  {
   "t": 82.8024,
   "stem": 0,
   "energy": 0.3179
  },
  {
   "t": 83.081,
   "stem": 3,
   "energy": 123.2938
  },
  {
   "t": 83.1971,
   "stem": 0,
   "energy": 0.2532
  },
  {
   "t": 83.3132,
   "stem": 3,
   "energy": 76.6447
  },
  {
   "t": 83.4757,
   "stem": 1,
   "energy": 0.0002
  },
  {
   "t": 83.5686,
   "stem": 3,
   "energy": 81.5093
  },
  {
   "t": 83.7544,
   "stem": 3,
   "energy": 32.2867
  },
  {
   "t": 83.824,
   "stem": 0,
   "energy": 1.1023
  },
  {
   "t": 83.9866,
   "stem": 3,
   "energy": 30.6602
  },
  {
   "t": 84.0562,
   "stem": 0,
   "energy": 20.1882
  },
  {
   "t": 84.3349,
   "stem": 3,
   "energy": 30.0441
  },
  {
   "t": 84.5439,
   "stem": 3,
   "energy": 16.8875
  },
  {
   "t": 84.7761,
   "stem": 3,
   "energy": 43.0412
  },
  {
   "t": 84.8225,
   "stem": 0,
   "energy": 0.9042
  },
  {
   "t": 85.0547,
   "stem": 3,
   "energy": 48.3533
  },
  {
   "t": 85.194,
   "stem": 0,
   "energy": 0.3975
  },
  {
   "t": 85.3101,
   "stem": 0,
   "energy": 36.358
  },
  {
   "t": 85.5423,
   "stem": 3,
   "energy": 22.0389
  },
  {
   "t": 85.821,
   "stem": 3,
   "energy": 46.0703
  },
  {
   "t": 86.0764,
   "stem": 3,
   "energy": 130.4782
  },
  {
   "t": 86.3318,
   "stem": 3,
   "energy": 36.0965
  },
  {
   "t": 86.4943,
   "stem": 0,
   "energy": 0.0004
  },
  {
   "t": 86.564,
   "stem": 3,
   "energy": 72.3202
  },
  {
   "t": 86.7265,
   "stem": 3,
   "energy": 35.4239
  },
  {
   "t": 86.773,
   "stem": 0,
   "energy": 0.0061
  },
  {
   "t": 86.8194,
   "stem": 6,
   "energy": 17.6311
  },
  {
   "t": 86.9123,
   "stem": 1,
   "energy": 18.0795
  },
  {
   "t": 87.0516,
   "stem": 3,
   "energy": 40.1758
  },
  {
   "t": 87.1677,
   "stem": 0,
   "energy": 1.3753
  },
  {
   "t": 87.307,
   "stem": 3,
   "energy": 45.0308
  },
  {
   "t": 87.516,
   "stem": 3,
   "energy": 16.7746
  },
  {
   "t": 87.7482,
   "stem": 0,
   "energy": 0.0135
  },
  {
   "t": 87.8179,
   "stem": 3,
   "energy": 96.9894
  },
  {
   "t": 88.0733,
   "stem": 3,
   "energy": 127.4029
  },
  {
   "t": 88.3055,
   "stem": 0,
   "energy": 0.7162
  },
  {
   "t": 88.4912,
   "stem": 1,
   "energy": 0.0
  },
  {
   "t": 88.5609,
   "stem": 3,
   "energy": 49.6379
  },
  {
   "t": 88.8163,
   "stem": 3,
   "energy": 42.3501
  },
  {
   "t": 88.9324,
   "stem": 1,
   "energy": 1.0164
  },
  {
   "t": 89.0717,
   "stem": 3,
   "energy": 130.6406
  },
  {
   "t": 89.1878,
   "stem": 0,
   "energy": 0.3478
  },
  {
   "t": 89.2807,
   "stem": 3,
   "energy": 41.473
  },
  {
   "t": 89.5594,
   "stem": 3,
   "energy": 69.9668
  },
  {
   "t": 89.7219,
   "stem": 3,
   "energy": 45.5216
  },
  {
   "t": 89.7683,
   "stem": 1,
   "energy": 18.4682
  },
  {
   "t": 90.0702,
   "stem": 3,
   "energy": 144.9806
  },
  {
   "t": 90.3024,
   "stem": 0,
   "energy": 0.2301
  },
  {
   "t": 90.5114,
   "stem": 3,
   "energy": 13.354
  },
  {
   "t": 90.5578,
   "stem": 1,
   "energy": 0.7098
  },
  {
   "t": 90.8365,
   "stem": 3,
   "energy": 40.2465
  },
  {
   "t": 91.0687,
   "stem": 3,
   "energy": 126.7952
  },
  {
   "t": 91.1848,
   "stem": 0,
   "energy": 0.2609
  },
  {
   "t": 91.3009,
   "stem": 3,
   "energy": 49.6087
  },
  {
   "t": 91.5331,
   "stem": 3,
   "energy": 17.1086
  },
  {
   "t": 91.6956,
   "stem": 3,
   "energy": 30.6983
  },
  {
   "t": 91.8117,
   "stem": 0,
   "energy": 0.7707
  },
  {
   "t": 92.0207,
   "stem": 1,
   "energy": 17.0484
  },
  {
   "t": 92.0671,
   "stem": 3,
   "energy": 89.7017
  },
  {
   "t": 92.3225,
   "stem": 3,
   "energy": 36.1216
  },
  {
   "t": 92.5547,
   "stem": 3,
   "energy": 49.1531
  },
  {
   "t": 92.7869,
   "stem": 0,
   "energy": 0.0107
  },
  {
   "t": 92.9959,
   "stem": 6,
   "energy": 20.3887
  },
  {
   "t": 93.0656,
   "stem": 0,
   "energy": 47.7928
  },
  {
   "t": 93.1817,
   "stem": 0,
   "energy": 0.2458
  },
  {
   "t": 93.2746,
   "stem": 0,
   "energy": 0.0011
  },
  {
   "t": 93.321,
   "stem": 3,
   "energy": 107.1084
  },
  {
   "t": 93.4603,
   "stem": 0,
   "energy": 0.0187
  },
  {
   "t": 93.5764,
   "stem": 3,
   "energy": 89.7447
  },
  {
   "t": 93.8086,
   "stem": 3,
   "energy": 38.4004
  },
  {
   "t": 94.0176,
   "stem": 6,
   "energy": 22.294
  },
  {
   "t": 94.064,
   "stem": 0,
   "energy": 49.1216
  },
  {
   "t": 94.2962,
   "stem": 0,
   "energy": 0.1329
  },
  {
   "t": 94.5517,
   "stem": 3,
   "energy": 19.3182
  },
  {
   "t": 94.7374,
   "stem": 0,
   "energy": 0.0172
  },
  {
   "t": 94.9464,
   "stem": 1,
   "energy": 5.487
  },
  {
   "t": 95.0625,
   "stem": 0,
   "energy": 34.3503
  },
  {
   "t": 95.1786,
   "stem": 0,
   "energy": 0.446
  },
  {
   "t": 95.2947,
   "stem": 3,
   "energy": 27.2003
  },
  {
   "t": 95.5733,
   "stem": 3,
   "energy": 78.2408
  },
  {
   "t": 95.643,
   "stem": 6,
   "energy": 4.4975
  },
  {
   "t": 95.7823,
   "stem": 1,
   "energy": 15.9245
  },
  {
   "t": 95.8288,
   "stem": 3,
   "energy": 26.5226
  },
  {
   "t": 96.061,
   "stem": 0,
   "energy": 29.5385
  },
  {
   "t": 96.1538,
   "stem": 6,
   "energy": 2.34
  },
  {
   "t": 96.2932,
   "stem": 3,
   "energy": 22.1626
  },
  {
   "t": 96.3396,
   "stem": 0,
   "energy": 1.7009
  },
  {
   "t": 96.4093,
   "stem": 6,
   "energy": 1.9058
  },
  {
   "t": 96.5254,
   "stem": 6,
   "energy": 2.1721
  },
  {
   "t": 96.5718,
   "stem": 3,
   "energy": 81.0693
  },
  {
   "t": 96.6647,
   "stem": 6,
   "energy": 0.9687
  },
  {
   "t": 96.7808,
   "stem": 3,
   "energy": 17.5563
  },
  {
   "t": 96.8272,
   "stem": 0,
   "energy": 1.219
  },
  {
   "t": 96.9201,
   "stem": 6,
   "energy": 1.6346
  },
  {
   "t": 97.0594,
   "stem": 0,
   "energy": 32.0699
  },
  {
   "t": 97.1755,
   "stem": 3,
   "energy": 19.1307
  },
  {
   "t": 97.2916,
   "stem": 3,
   "energy": 20.0674
  },
  {
   "t": 97.4077,
   "stem": 6,
   "energy": 1.5863
  },
  {
   "t": 97.5006,
   "stem": 0,
   "energy": 0.0035
  },
  {
   "t": 97.547,
   "stem": 3,
   "energy": 22.4201
  },
  {
   "t": 97.6631,
   "stem": 6,
   "energy": 1.5887
  },
  {
   "t": 97.7792,
   "stem": 3,
   "energy": 15.7779
  },
  {
   "t": 97.9185,
   "stem": 6,
   "energy": 2.0135
  },
  {
   "t": 98.0579,
   "stem": 0,
   "energy": 24.8349
  },
  {
   "t": 98.174,
   "stem": 3,
   "energy": 18.3692
  },
  {
   "t": 98.2901,
   "stem": 3,
   "energy": 20.8201
  },
  {
   "t": 98.4294,
   "stem": 6,
   "energy": 3.7243
  },
  {
   "t": 98.499,
   "stem": 0,
   "energy": 0.0002
  },
  {
   "t": 98.5455,
   "stem": 3,
   "energy": 20.3623
  },
  {
   "t": 98.6616,
   "stem": 6,
   "energy": 1.7971
  },
  {
   "t": 98.7777,
   "stem": 3,
   "energy": 19.3771
  },
  {
   "t": 98.8241,
   "stem": 0,
   "energy": 1.1163
  },
  {
   "t": 98.917,
   "stem": 3,
   "energy": 20.2985
  },
  {
   "t": 99.0331,
   "stem": 3,
   "energy": 18.037
  },
  {
   "t": 99.1724,
   "stem": 3,
   "energy": 18.0401
  },
  {
   "t": 99.3117,
   "stem": 0,
   "energy": 42.2641
  },
  {
   "t": 99.4278,
   "stem": 6,
   "energy": 1.6825
  },
  {
   "t": 99.4743,
   "stem": 0,
   "energy": 0.0053
  },
  {
   "t": 99.5439,
   "stem": 3,
   "energy": 18.6446
  },
  {
   "t": 99.66,
   "stem": 6,
   "energy": 1.5725
  },
  {
   "t": 99.7994,
   "stem": 3,
   "energy": 25.8198
  },
  {
   "t": 99.9387,
   "stem": 3,
   "energy": 64.7115
  },
  {
   "t": 100.0316,
   "stem": 6,
   "energy": 1.6165
  },
  {
   "t": 100.078,
   "stem": 3,
   "energy": 131.3842
  },
  {
   "t": 100.287,
   "stem": 6,
   "energy": 4.3831
  },
  {
   "t": 100.4263,
   "stem": 6,
   "energy": 4.797
  },
  {
   "t": 100.5656,
   "stem": 0,
   "energy": 42.7693
  },
  {
   "t": 100.6585,
   "stem": 6,
   "energy": 4.1327
  },
  {
   "t": 100.7282,
   "stem": 0,
   "energy": 0.0623
  },
  {
   "t": 100.7746,
   "stem": 3,
   "energy": 20.1553
  },
  {
   "t": 101.0532,
   "stem": 3,
   "energy": 31.3973
  },
  {
   "t": 101.1693,
   "stem": 3,
   "energy": 18.0238
  },
  {
   "t": 101.2854,
   "stem": 0,
   "energy": 0.0122
  },
  {
   "t": 101.3319,
   "stem": 3,
   "energy": 28.2712
  },
  {
   "t": 101.448,
   "stem": 6,
   "energy": 7.996
  },
  {
   "t": 101.5641,
   "stem": 0,
   "energy": 48.2144
  },
  {
   "t": 101.7034,
   "stem": 6,
   "energy": 10.4188
  },
  {
   "t": 101.8195,
   "stem": 3,
   "energy": 23.9193
  },
  {
   "t": 101.9124,
   "stem": 6,
   "energy": 2.067
  },
  {
   "t": 102.0517,
   "stem": 3,
   "energy": 28.1113
  },
  {
   "t": 102.3071,
   "stem": 0,
   "energy": 0.739
  },
  {
   "t": 102.4232,
   "stem": 6,
   "energy": 3.742
  },
  {
   "t": 102.5625,
   "stem": 3,
   "energy": 67.4742
  },
  {
   "t": 102.7715,
   "stem": 3,
   "energy": 21.283
  },
  {
   "t": 102.818,
   "stem": 0,
   "energy": 1.1142
  },
  {
   "t": 102.9108,
   "stem": 6,
   "energy": 4.2665
  },
  {
   "t": 103.0734,
   "stem": 0,
   "energy": 77.3258
  },
  {
   "t": 103.1663,
   "stem": 3,
   "energy": 23.5008
  },
  {
   "t": 103.3288,
   "stem": 3,
   "energy": 32.2231
  },
  {
   "t": 103.3985,
   "stem": 6,
   "energy": 5.3369
  },
  {
   "t": 103.561,
   "stem": 0,
   "energy": 35.4036
  },
  {
   "t": 103.6539,
   "stem": 6,
   "energy": 3.0189
  },
  {
   "t": 103.7932,
   "stem": 3,
   "energy": 19.5317
  },
  {
   "t": 103.9093,
   "stem": 6,
   "energy": 3.4104
  },
  {
   "t": 104.0486,
   "stem": 3,
   "energy": 22.9583
  },
  {
   "t": 104.4201,
   "stem": 6,
   "energy": 5.5349
  },
  {
   "t": 104.5595,
   "stem": 3,
   "energy": 57.5196
  },
  {
   "t": 104.7917,
   "stem": 6,
   "energy": 3.0428
  },
  {
   "t": 104.8381,
   "stem": 3,
   "energy": 33.2531
  },
  {
   "t": 104.9078,
   "stem": 6,
   "energy": 4.2861
  },
  {
   "t": 105.0703,
   "stem": 3,
   "energy": 120.6802
  },
  {
   "t": 105.3257,
   "stem": 3,
   "energy": 30.8068
  },
  {
   "t": 105.5579,
   "stem": 3,
   "energy": 45.2905
  },
  {
   "t": 105.7901,
   "stem": 6,
   "energy": 3.6702
  },
  {
   "t": 106.0455,
   "stem": 3,
   "energy": 22.4463
  }
 ]
}