{
 "version": 1,
 "generator": "librosa-0.11.0",
 "bpm_input": 60,
 "bpm_detected": 60.1,
 "sr": 22050,
 "onsets": [
  {
   "t": 0.0464,
   "stem": 3,
   "energy": 56.6106
  },
  {
   "t": 0.3019,
   "stem": 3,
   "energy": 0.0281
  },
  {
   "t": 0.3947,
   "stem": 0,
   "energy": 0.0047
  },
  {
   "t": 0.5573,
   "stem": 0,
   "energy": 23.0475
  },
  {
   "t": 0.6502,
   "stem": 3,
   "energy": 0.0246
  },
  {
   "t": 0.7895,
   "stem": 3,
   "energy": 17.4541
  },
  {
   "t": 1.0449,
   "stem": 0,
   "energy": 0.3556
  },
  {
   "t": 1.161,
   "stem": 0,
   "energy": 0.1896
  },
  {
   "t": 1.3932,
   "stem": 0,
   "energy": 0.0044
  },
  {
   "t": 1.5325,
   "stem": 0,
   "energy": 0.3687
  },
  {
   "t": 1.7647,
   "stem": 0,
   "energy": 0.0079
  },
  {
   "t": 2.0201,
   "stem": 0,
   "energy": 0.023
  },
  {
   "t": 2.322,
   "stem": 0,
   "energy": 0.0227
  },
  {
   "t": 2.3917,
   "stem": 0,
   "energy": 0.0093
  },
  {
   "t": 2.531,
   "stem": 3,
   "energy": 0.0255
  },
  {
   "t": 2.6703,
   "stem": 0,
   "energy": 0.0182
  },
  {
   "t": 2.7632,
   "stem": 0,
   "energy": 0.005
  },
  {
   "t": 3.0186,
   "stem": 0,
   "energy": 0.0188
  },
  {
   "t": 3.1579,
   "stem": 3,
   "energy": 0.0462
  },
  {
   "t": 3.4366,
   "stem": 3,
   "energy": 0.0148
  },
  {
   "t": 3.5294,
   "stem": 3,
   "energy": 0.008
  },
  {
   "t": 3.7849,
   "stem": 0,
   "energy": 0.0082
  },
  {
   "t": 3.9474,
   "stem": 0,
   "energy": 0.1362
  },
  {
   "t": 4.0635,
   "stem": 0,
   "energy": 60.2682
  },
  {
   "t": 4.2725,
   "stem": 0,
   "energy": 0.026
  },
  {
   "t": 4.3189,
   "stem": 3,
   "energy": 0.0269
  },
  {
   "t": 4.3886,
   "stem": 0,
   "energy": 0.0071
  },
  {
   "t": 4.5511,
   "stem": 0,
   "energy": 28.4103
  },
  {
   "t": 4.6672,
   "stem": 3,
   "energy": 0.0158
  },
  {
   "t": 4.7833,
   "stem": 3,
   "energy": 3.012
  },
  {
   "t": 5.0387,
   "stem": 0,
   "energy": 0.1542
  },
  {
   "t": 5.178,
   "stem": 0,
   "energy": 0.5478
  },
  {
   "t": 5.4335,
   "stem": 0,
   "energy": 0.0157
  },
  {
   "t": 5.5263,
   "stem": 0,
   "energy": 0.0021
  },
  {
   "t": 5.7818,
   "stem": 3,
   "energy": 1.6134
  },
  {
   "t": 6.014,
   "stem": 0,
   "energy": 0.027
  },
  {
   "t": 6.2694,
   "stem": 3,
   "energy": 0.0401
  },
  {
   "t": 6.3855,
   "stem": 0,
   "energy": 0.0103
  },
  {
   "t": 6.548,
   "stem": 3,
   "energy": 31.6934
  },
  {
   "t": 6.6641,
   "stem": 0,
   "energy": 0.0201
  },
  {
   "t": 6.7802,
   "stem": 3,
   "energy": 0.3158
  },
  {
   "t": 7.0356,
   "stem": 3,
   "energy": 5.2647
  },
  {
   "t": 7.175,
   "stem": 3,
   "energy": 35.5795
  },
  {
   "t": 7.3839,
   "stem": 3,
   "energy": 0.0242
  },
  {
   "t": 7.5233,
   "stem": 3,
   "energy": 0.0809
  },
  {
   "t": 7.6161,
   "stem": 6,
   "energy": 0.0298
  },
  {
   "t": 7.7555,
   "stem": 3,
   "energy": 0.407
  },
  {
   "t": 8.0573,
   "stem": 0,
   "energy": 48.2974
  },
  {
   "t": 8.3824,
   "stem": 3,
   "energy": 2.422
  },
  {
   "t": 8.4288,
   "stem": 6,
   "energy": 1.8836
  },
  {
   "t": 8.5217,
   "stem": 3,
   "energy": 55.954
  },
  {
   "t": 8.7771,
   "stem": 3,
   "energy": 2.929
  },
  {
   "t": 9.0558,
   "stem": 3,
   "energy": 2.1138
  },
  {
   "t": 9.1254,
   "stem": 3,
   "energy": 2.9598
  },
  {
   "t": 9.1719,
   "stem": 0,
   "energy": 0.2694
  },
  {
   "t": 9.5434,
   "stem": 3,
   "energy": 2.9779
  },
  {
   "t": 9.7524,
   "stem": 3,
   "energy": 1.7307
  },
  {
   "t": 9.7988,
   "stem": 0,
   "energy": 26.0775
  },
  {
   "t": 10.031,
   "stem": 3,
   "energy": 4.1884
  },
  {
   "t": 10.4025,
   "stem": 3,
   "energy": 1.3928
  },
  {
   "t": 10.5186,
   "stem": 3,
   "energy": 1.7991
  },
  {
   "t": 10.7508,
   "stem": 3,
   "energy": 1.817
  },
  {
   "t": 10.8669,
   "stem": 6,
   "energy": 1.7264
  },
  {
   "t": 11.0527,
   "stem": 3,
   "energy": 2.034
  },
  {
   "t": 11.1688,
   "stem": 3,
   "energy": 2.2479
  },
  {
   "t": 11.5403,
   "stem": 3,
   "energy": 3.162
  },
  {
   "t": 11.8886,
   "stem": 0,
   "energy": 0.0004
  },
  {
   "t": 11.9351,
   "stem": 6,
   "energy": 1.2303
  },
  {
   "t": 12.0279,
   "stem": 3,
   "energy": 1.4373
  },
  {
   "t": 12.4227,
   "stem": 0,
   "energy": 26.9504
  },
  {
   "t": 12.5388,
   "stem": 0,
   "energy": 40.2102
  },
  {
   "t": 12.7942,
   "stem": 0,
   "energy": 21.5732
  },
  {
   "t": 12.8639,
   "stem": 6,
   "energy": 0.5979
  },
  {
   "t": 13.0496,
   "stem": 3,
   "energy": 2.1632
  },
  {
   "t": 13.1425,
   "stem": 3,
   "energy": 1.3445
  },
  {
   "t": 13.4211,
   "stem": 0,
   "energy": 0.0029
  },
  {
   "t": 13.5605,
   "stem": 3,
   "energy": 2.8078
  },
  {
   "t": 13.6766,
   "stem": 6,
   "energy": 1.1804
  },
  {
   "t": 13.7694,
   "stem": 3,
   "energy": 0.9847
  },
  {
   "t": 14.0481,
   "stem": 3,
   "energy": 27.4482
  },
  {
   "t": 14.3964,
   "stem": 3,
   "energy": 0.9483
  },
  {
   "t": 14.4893,
   "stem": 6,
   "energy": 0.67
  },
  {
   "t": 14.5589,
   "stem": 0,
   "energy": 20.7297
  },
  {
   "t": 14.675,
   "stem": 0,
   "energy": 0.0093
  },
  {
   "t": 14.7447,
   "stem": 3,
   "energy": 1.3283
  },
  {
   "t": 14.8608,
   "stem": 6,
   "energy": 0.9961
  },
  {
   "t": 15.0465,
   "stem": 3,
   "energy": 24.162
  },
  {
   "t": 15.1394,
   "stem": 3,
   "energy": 76.1861
  },
  {
   "t": 15.5574,
   "stem": 3,
   "energy": 6.3241
  },
  {
   "t": 15.7896,
   "stem": 3,
   "energy": 2.4243
  },
  {
   "t": 16.3701,
   "stem": 3,
   "energy": 19.6043
  },
  {
   "t": 16.788,
   "stem": 3,
   "energy": 6.5671
  },
  {
   "t": 17.0667,
   "stem": 3,
   "energy": 7.2841
  },
  {
   "t": 17.1595,
   "stem": 3,
   "energy": 8.0173
  },
  {
   "t": 17.2989,
   "stem": 3,
   "energy": 3.7249
  },
  {
   "t": 17.5543,
   "stem": 3,
   "energy": 10.187
  },
  {
   "t": 17.7633,
   "stem": 0,
   "energy": 1.0246
  },
  {
   "t": 17.8097,
   "stem": 3,
   "energy": 3.8278
  },
  {
   "t": 18.0187,
   "stem": 3,
   "energy": 4.8651
  },
  {
   "t": 18.2741,
   "stem": 0,
   "energy": 0.4483
  },
  {
   "t": 18.4366,
   "stem": 3,
   "energy": 3.9764
  },
  {
   "t": 18.8082,
   "stem": 3,
   "energy": 1.8442
  },
  {
   "t": 18.8546,
   "stem": 6,
   "energy": 0.0635
  },
  {
   "t": 19.0404,
   "stem": 3,
   "energy": 0.7737
  },
  {
   "t": 19.1797,
   "stem": 0,
   "energy": 0.4771
  },
  {
   "t": 19.2958,
   "stem": 3,
   "energy": 0.8369
  },
  {
   "t": 19.528,
   "stem": 3,
   "energy": 1.0589
  },
  {
   "t": 19.7834,
   "stem": 3,
   "energy": 0.7785
  },
  {
   "t": 20.0156,
   "stem": 6,
   "energy": 0.0459
  },
  {
   "t": 20.062,
   "stem": 0,
   "energy": 46.6883
  },
  {
   "t": 20.4103,
   "stem": 3,
   "energy": 5.2162
  },
  {
   "t": 20.5264,
   "stem": 3,
   "energy": 9.2086
  },
  {
   "t": 20.7586,
   "stem": 1,
   "energy": 0.0028
  },
  {
   "t": 20.8051,
   "stem": 3,
   "energy": 38.1459
  },
  {
   "t": 21.0605,
   "stem": 0,
   "energy": 45.5576
  },
  {
   "t": 21.1534,
   "stem": 0,
   "energy": 57.7845
  },
  {
   "t": 21.4088,
   "stem": 3,
   "energy": 1.2954
  },
  {
   "t": 21.5017,
   "stem": 0,
   "energy": 0.2953
  },
  {
   "t": 21.5481,
   "stem": 3,
   "energy": 15.5717
  },
  {
   "t": 21.8035,
   "stem": 3,
   "energy": 34.6852
  },
  {
   "t": 22.0357,
   "stem": 0,
   "energy": 4.2244
  },
  {
   "t": 22.2912,
   "stem": 3,
   "energy": 0.3031
  },
  {
   "t": 22.4305,
   "stem": 1,
   "energy": 6.2929
  },
  {
   "t": 22.5466,
   "stem": 3,
   "energy": 15.0542
  },
  {
   "t": 22.7788,
   "stem": 3,
   "energy": 0.0249
  },
  {
   "t": 22.8717,
   "stem": 6,
   "energy": 0.0001
  },
  {
   "t": 23.0342,
   "stem": 3,
   "energy": 4.035
  },
  {
   "t": 23.1735,
   "stem": 3,
   "energy": 34.3783
  },
  {
   "t": 23.4289,
   "stem": 3,
   "energy": 6.3479
  },
  {
   "t": 23.545,
   "stem": 3,
   "energy": 10.0828
  },
  {
   "t": 23.6611,
   "stem": 1,
   "energy": 0.0505
  },
  {
   "t": 23.8005,
   "stem": 3,
   "energy": 4.9444
  },
  {
   "t": 23.9166,
   "stem": 3,
   "energy": 13.5559
  },
  {
   "t": 24.0559,
   "stem": 3,
   "energy": 42.6631
  },
  {
   "t": 24.381,
   "stem": 3,
   "energy": 0.0038
  },
  {
   "t": 24.4274,
   "stem": 0,
   "energy": 0.2419
  },
  {
   "t": 24.5435,
   "stem": 3,
   "energy": 14.4029
  },
  {
   "t": 24.6596,
   "stem": 0,
   "energy": 0.0012
  },
  {
   "t": 24.7989,
   "stem": 1,
   "energy": 1.8555
  },
  {
   "t": 25.0079,
   "stem": 3,
   "energy": 0.893
  },
  {
   "t": 25.1704,
   "stem": 3,
   "energy": 38.0436
  },
  {
   "t": 25.3794,
   "stem": 1,
   "energy": 0.5109
  },
  {
   "t": 25.4259,
   "stem": 3,
   "energy": 7.6016
  },
  {
   "t": 25.542,
   "stem": 3,
   "energy": 17.2854
  },
  {
   "t": 25.7974,
   "stem": 3,
   "energy": 31.7123
  },
  {
   "t": 26.0528,
   "stem": 1,
   "energy": 2.8837
  },
  {
   "t": 26.3546,
   "stem": 6,
   "energy": 0.0
  },
  {
   "t": 26.4243,
   "stem": 0,
   "energy": 22.201
  },
  {
   "t": 26.5404,
   "stem": 0,
   "energy": 32.9997
  },
  {
   "t": 26.7958,
   "stem": 3,
   "energy": 27.2571
  },
  {
   "t": 27.0512,
   "stem": 0,
   "energy": 32.6379
  },
  {
   "t": 27.1673,
   "stem": 3,
   "energy": 40.7239
  },
  {
   "t": 27.4228,
   "stem": 3,
   "energy": 3.3285
  },
  {
   "t": 27.5389,
   "stem": 3,
   "energy": 12.7635
  },
  {
   "t": 27.7943,
   "stem": 3,
   "energy": 1.6913
  },
  {
   "t": 27.9568,
   "stem": 6,
   "energy": 0.0
  },
  {
   "t": 28.0033,
   "stem": 1,
   "energy": 0.3358
  },
  {
   "t": 28.0497,
   "stem": 0,
   "energy": 24.6593
  },
  {
   "t": 28.2819,
   "stem": 0,
   "energy": 0.0039
  },
  {
   "t": 28.398,
   "stem": 3,
   "energy": 1.1679
  },
  {
   "t": 28.5373,
   "stem": 3,
   "energy": 16.2848
  },
  {
   "t": 28.6534,
   "stem": 0,
   "energy": 0.0031
  },
  {
   "t": 28.6999,
   "stem": 6,
   "energy": 1.2599
  },
  {
   "t": 28.7927,
   "stem": 0,
   "energy": 17.6808
  },
  {
   "t": 29.0249,
   "stem": 3,
   "energy": 1.6514
  },
  {
   "t": 29.1178,
   "stem": 1,
   "energy": 0.0412
  },
  {
   "t": 29.1875,
   "stem": 3,
   "energy": 41.9451
  },
  {
   "t": 29.3036,
   "stem": 0,
   "energy": 0.0072
  },
  {
   "t": 29.4197,
   "stem": 1,
   "energy": 3.2825
  },
  {
   "t": 29.5358,
   "stem": 3,
   "energy": 20.7209
  },
  {
   "t": 29.7912,
   "stem": 1,
   "energy": 1.6555
  },
  {
   "t": 30.0466,
   "stem": 0,
   "energy": 19.4963
  },
  {
   "t": 30.302,
   "stem": 0,
   "energy": 0.0082
  },
  {
   "t": 30.4181,
   "stem": 3,
   "energy": 7.342
  },
  {
   "t": 30.5342,
   "stem": 3,
   "energy": 21.5182
  },
  {
   "t": 30.6736,
   "stem": 0,
   "energy": 0.0199
  },
  {
   "t": 30.7897,
   "stem": 0,
   "energy": 14.0647
  },
  {
   "t": 30.8825,
   "stem": 6,
   "energy": 0.8451
  },
  {
   "t": 31.0451,
   "stem": 0,
   "energy": 21.9461
  },
  {
   "t": 31.1147,
   "stem": 6,
   "energy": 0.6015
  },
  {
   "t": 31.1844,
   "stem": 3,
   "energy": 25.5611
  },
  {
   "t": 31.2773,
   "stem": 0,
   "energy": 0.0067
  },
  {
   "t": 31.4166,
   "stem": 3,
   "energy": 5.1856
  },
  {
   "t": 31.5095,
   "stem": 3,
   "energy": 17.3545
  },
  {
   "t": 31.5559,
   "stem": 6,
   "energy": 2.2916
  },
  {
   "t": 31.8113,
   "stem": 3,
   "energy": 9.7873
  },
  {
   "t": 32.0435,
   "stem": 3,
   "energy": 30.3136
  },
  {
   "t": 32.4151,
   "stem": 1,
   "energy": 2.094
  },
  {
   "t": 32.5312,
   "stem": 3,
   "energy": 16.6016
  },
  {
   "t": 32.7866,
   "stem": 0,
   "energy": 6.887
  },
  {
   "t": 33.042,
   "stem": 0,
   "energy": 18.2943
  },
  {
   "t": 33.1581,
   "stem": 3,
   "energy": 50.2556
  },
  {
   "t": 33.4135,
   "stem": 3,
   "energy": 1.8677
  },
  {
   "t": 33.5296,
   "stem": 3,
   "energy": 17.5794
  },
  {
   "t": 33.7386,
   "stem": 1,
   "energy": 0.0024
  },
  {
   "t": 33.785,
   "stem": 0,
   "energy": 2.5502
  },
  {
   "t": 34.0405,
   "stem": 3,
   "energy": 18.0435
  },
  {
   "t": 34.3655,
   "stem": 1,
   "energy": 0.0116
  },
  {
   "t": 34.412,
   "stem": 3,
   "energy": 1.0084
  },
  {
   "t": 34.5281,
   "stem": 3,
   "energy": 10.5596
  },
  {
   "t": 34.621,
   "stem": 6,
   "energy": 0.1307
  },
  {
   "t": 34.7835,
   "stem": 3,
   "energy": 2.8536
  },
  {
   "t": 34.9925,
   "stem": 3,
   "energy": 3.6947
  },
  {
   "t": 35.0389,
   "stem": 0,
   "energy": 10.6793
  },
  {
   "t": 35.155,
   "stem": 3,
   "energy": 56.976
  },
  {
   "t": 35.4337,
   "stem": 1,
   "energy": 6.8062
  },
  {
   "t": 35.5265,
   "stem": 3,
   "energy": 11.5382
  },
  {
   "t": 35.782,
   "stem": 3,
   "energy": 0.5571
  },
  {
   "t": 35.898,
   "stem": 0,
   "energy": 0.0009
  },
  {
   "t": 36.0374,
   "stem": 3,
   "energy": 13.1354
  },
  {
   "t": 36.3857,
   "stem": 3,
   "energy": 0.1369
  },
  {
   "t": 36.4321,
   "stem": 1,
   "energy": 7.9196
  },
  {
   "t": 36.525,
   "stem": 3,
   "energy": 16.594
  },
  {
   "t": 36.5714,
   "stem": 6,
   "energy": 0.0282
  },
  {
   "t": 36.7107,
   "stem": 5,
   "energy": 0.0
  },
  {
   "t": 36.7804,
   "stem": 3,
   "energy": 0.5303
  },
  {
   "t": 36.9894,
   "stem": 3,
   "energy": 3.7092
  },
  {
   "t": 37.0358,
   "stem": 0,
   "energy": 6.0063
  },
  {
   "t": 37.1519,
   "stem": 3,
   "energy": 55.1847
  },
  {
   "t": 37.3145,
   "stem": 6,
   "energy": 0.1215
  },
  {
   "t": 37.4073,
   "stem": 3,
   "energy": 0.2635
  },
  {
   "t": 37.5234,
   "stem": 3,
   "energy": 16.9758
  },
  {
   "t": 37.8021,
   "stem": 0,
   "energy": 25.6098
  },
  {
   "t": 38.0575,
   "stem": 3,
   "energy": 50.4062
  },
  {
   "t": 38.429,
   "stem": 1,
   "energy": 5.2564
  },
  {
   "t": 38.5451,
   "stem": 0,
   "energy": 22.8432
  },
  {
   "t": 38.6612,
   "stem": 1,
   "energy": 0.4626
  },
  {
   "t": 38.8005,
   "stem": 3,
   "energy": 31.9046
  },
  {
   "t": 39.0095,
   "stem": 3,
   "energy": 2.521
  },
  {
   "t": 39.1488,
   "stem": 3,
   "energy": 65.885
  },
  {
   "t": 39.3114,
   "stem": 6,
   "energy": 0.0428
  },
  {
   "t": 39.4275,
   "stem": 3,
   "energy": 4.0189
  },
  {
   "t": 39.5436,
   "stem": 3,
   "energy": 15.38
  },
  {
   "t": 39.799,
   "stem": 1,
   "energy": 5.5657
  },
  {
   "t": 39.9848,
   "stem": 0,
   "energy": 0.0007
  },
  {
   "t": 40.0312,
   "stem": 3,
   "energy": 0.8623
  },
  {
   "t": 40.4259,
   "stem": 3,
   "energy": 5.9333
  },
  {
   "t": 40.4956,
   "stem": 6,
   "energy": 0.0484
  },
  {
   "t": 40.542,
   "stem": 3,
   "energy": 14.4714
  },
  {
   "t": 40.7278,
   "stem": 1,
   "energy": 0.0011
  },
  {
   "t": 40.7975,
   "stem": 3,
   "energy": 27.5147
  },
  {
   "t": 41.0064,
   "stem": 3,
   "energy": 1.7676
  },
  {
   "t": 41.1225,
   "stem": 1,
   "energy": 0.0023
  },
  {
   "t": 41.169,
   "stem": 3,
   "energy": 39.1607
  },
  {
   "t": 41.2619,
   "stem": 6,
   "energy": 0.2479
  },
  {
   "t": 41.4012,
   "stem": 3,
   "energy": 0.9258
  },
  {
   "t": 41.5405,
   "stem": 3,
   "energy": 12.4256
  },
  {
   "t": 41.7959,
   "stem": 1,
   "energy": 5.0985
  },
  {
   "t": 41.8888,
   "stem": 6,
   "energy": 0.3701
  },
  {
   "t": 41.9817,
   "stem": 0,
   "energy": 0.215
  },
  {
   "t": 42.0513,
   "stem": 3,
   "energy": 6.5273
  },
  {
   "t": 42.4229,
   "stem": 3,
   "energy": 7.3586
  },
  {
   "t": 42.8176,
   "stem": 3,
   "energy": 15.1002
  },
  {
   "t": 43.0034,
   "stem": 6,
   "energy": 0.8039
  },
  {
   "t": 43.7928,
   "stem": 0,
   "energy": 2.762
  },
  {
   "t": 43.9786,
   "stem": 6,
   "energy": 0.5218
  },
  {
   "t": 44.0483,
   "stem": 3,
   "energy": 26.0983
  },
  {
   "t": 44.443,
   "stem": 3,
   "energy": 91.1206
  },
  {
   "t": 44.5127,
   "stem": 3,
   "energy": 42.9219
  },
  {
   "t": 44.8145,
   "stem": 3,
   "energy": 79.7921
  },
  {
   "t": 45.0467,
   "stem": 3,
   "energy": 37.1272
  },
  {
   "t": 45.1164,
   "stem": 6,
   "energy": 0.9215
  },
  {
   "t": 45.5576,
   "stem": 3,
   "energy": 15.4984
  },
  {
   "t": 45.7898,
   "stem": 3,
   "energy": 29.2558
  },
  {
   "t": 46.0452,
   "stem": 3,
   "energy": 46.861
  },
  {
   "t": 46.4167,
   "stem": 0,
   "energy": 0.323
  },
  {
   "t": 46.5328,
   "stem": 3,
   "energy": 21.3569
  },
  {
   "t": 46.765,
   "stem": 0,
   "energy": 0.0217
  },
  {
   "t": 46.8114,
   "stem": 3,
   "energy": 20.9738
  },
  {
   "t": 47.0436,
   "stem": 3,
   "energy": 22.5705
  },
  {
   "t": 47.4151,
   "stem": 0,
   "energy": 0.1506
  },
  {
   "t": 47.5545,
   "stem": 3,
   "energy": 25.8198
  },
  {
   "t": 47.6473,
   "stem": 6,
   "energy": 2.3086
  },
  {
   "t": 47.7867,
   "stem": 0,
   "energy": 0.2527
  },
  {
   "t": 48.0653,
   "stem": 3,
   "energy": 64.917
  },
  {
   "t": 48.1117,
   "stem": 6,
   "energy": 2.7562
  },
  {
   "t": 48.4368,
   "stem": 3,
   "energy": 70.846
  },
  {
   "t": 48.5065,
   "stem": 3,
   "energy": 92.3248
  },
  {
   "t": 48.5529,
   "stem": 0,
   "energy": 13.1708
  },
  {
   "t": 48.7619,
   "stem": 3,
   "energy": 19.5447
  },
  {
   "t": 49.0638,
   "stem": 3,
   "energy": 32.7621
  },
  {
   "t": 49.4121,
   "stem": 0,
   "energy": 0.064
  },
  {
   "t": 49.5282,
   "stem": 3,
   "energy": 30.8477
  },
  {
   "t": 49.5978,
   "stem": 5,
   "energy": 0.0526
  },
  {
   "t": 49.8068,
   "stem": 3,
   "energy": 54.6543
  },
  {
   "t": 50.039,
   "stem": 3,
   "energy": 39.5569
  },
  {
   "t": 50.1087,
   "stem": 6,
   "energy": 0.7458
  },
  {
   "t": 50.4105,
   "stem": 3,
   "energy": 27.0394
  },
  {
   "t": 50.5266,
   "stem": 3,
   "energy": 93.8995
  },
  {
   "t": 50.6195,
   "stem": 5,
   "energy": 0.0204
  },
  {
   "t": 50.8053,
   "stem": 3,
   "energy": 43.8201
  },
  {
   "t": 50.9214,
   "stem": 6,
   "energy": 1.4852
  },
  {
   "t": 50.991,
   "stem": 0,
   "energy": 0.212
  },
  {
   "t": 51.0607,
   "stem": 3,
   "energy": 57.3804
  },
  {
   "t": 51.5483,
   "stem": 3,
   "energy": 14.8095
  },
  {
   "t": 51.8037,
   "stem": 0,
   "energy": 0.5554
  },
  {
   "t": 52.0591,
   "stem": 3,
   "energy": 49.4101
  },
  {
   "t": 52.3842,
   "stem": 0,
   "energy": 0.0056
  },
  {
   "t": 52.4307,
   "stem": 3,
   "energy": 47.6239
  },
  {
   "t": 52.5235,
   "stem": 3,
   "energy": 32.295
  },
  {
   "t": 52.8022,
   "stem": 3,
   "energy": 44.9925
  },
  {
   "t": 52.9647,
   "stem": 6,
   "energy": 3.8287
  },
  {
   "t": 53.0576,
   "stem": 3,
   "energy": 28.1527
  },
  {
   "t": 53.2898,
   "stem": 0,
   "energy": 0.258
  },
  {
   "t": 53.522,
   "stem": 3,
   "energy": 21.1347
  },
  {
   "t": 53.8006,
   "stem": 3,
   "energy": 43.2834
  },
  {
   "t": 54.0561,
   "stem": 3,
   "energy": 47.9532
  },
  {
   "t": 54.2883,
   "stem": 0,
   "energy": 0.1889
  },
  {
   "t": 54.4044,
   "stem": 0,
   "energy": 0.0786
  },
  {
   "t": 54.474,
   "stem": 5,
   "energy": 0.0021
  },
  {
   "t": 54.5205,
   "stem": 3,
   "energy": 14.3735
  },
  {
   "t": 54.7759,
   "stem": 3,
   "energy": 13.5601
  },
  {
   "t": 54.9152,
   "stem": 0,
   "energy": 23.2744
  },
  {
   "t": 55.0545,
   "stem": 3,
   "energy": 24.5507
  },
  {
   "t": 55.426,
   "stem": 3,
   "energy": 23.3011
  },
  {
   "t": 55.5189,
   "stem": 3,
   "energy": 19.2113
  },
  {
   "t": 55.7743,
   "stem": 3,
   "energy": 18.7131
  },
  {
   "t": 55.8904,
   "stem": 6,
   "energy": 2.6466
  },
  {
   "t": 56.0065,
   "stem": 0,
   "energy": 0.0353
  },
  {
   "t": 56.053,
   "stem": 3,
   "energy": 57.1544
  },
  {
   "t": 56.4013,
   "stem": 3,
   "energy": 21.1736
  },
  {
   "t": 56.5174,
   "stem": 3,
   "energy": 67.3365
  },
  {
   "t": 56.796,
   "stem": 0,
   "energy": 22.3446
  },
  {
   "t": 57.0282,
   "stem": 3,
   "energy": 23.7891
  },
  {
   "t": 57.1211,
   "stem": 6,
   "energy": 1.9001
  },
  {
   "t": 57.3765,
   "stem": 3,
   "energy": 26.1134
  },
  {
   "t": 57.539,
   "stem": 3,
   "energy": 25.4916
  },
  {
   "t": 57.748,
   "stem": 3,
   "energy": 20.2576
  },
  {
   "t": 58.0499,
   "stem": 0,
   "energy": 27.2118
  },
  {
   "t": 58.0963,
   "stem": 6,
   "energy": 0.7719
  },
  {
   "t": 58.3982,
   "stem": 3,
   "energy": 21.1068
  },
  {
   "t": 58.5143,
   "stem": 3,
   "energy": 46.8255
  },
  {
   "t": 58.7929,
   "stem": 3,
   "energy": 30.6003
  },
  {
   "t": 58.8858,
   "stem": 1,
   "energy": 11.8287
  },
  {
   "t": 59.0483,
   "stem": 3,
   "energy": 42.6231
  },
  {
   "t": 59.118,
   "stem": 1,
   "energy": 10.1921
  },
  {
   "t": 59.4199,
   "stem": 0,
   "energy": 0.1567
  },
  {
   "t": 59.5592,
   "stem": 3,
   "energy": 22.3361
  },
  {
   "t": 59.7682,
   "stem": 0,
   "energy": 0.0045
  },
  {
   "t": 60.0468,
   "stem": 3,
   "energy": 37.3496
  },
  {
   "t": 60.4415,
   "stem": 3,
   "energy": 53.5704
  },
  {
   "t": 60.5344,
   "stem": 3,
   "energy": 72.4521
  },
  {
   "t": 60.6273,
   "stem": 6,
   "energy": 1.7964
  },
  {
   "t": 60.8131,
   "stem": 3,
   "energy": 66.113
  },
  {
   "t": 61.0453,
   "stem": 3,
   "energy": 21.0134
  },
  {
   "t": 61.1149,
   "stem": 6,
   "energy": 1.4728
  },
  {
   "t": 61.4168,
   "stem": 0,
   "energy": 0.208
  },
  {
   "t": 61.5097,
   "stem": 3,
   "energy": 17.1059
  },
  {
   "t": 61.7883,
   "stem": 3,
   "energy": 25.8726
  },
  {
   "t": 62.0437,
   "stem": 0,
   "energy": 21.4053
  },
  {
   "t": 62.2527,
   "stem": 0,
   "energy": 0.1337
  },
  {
   "t": 62.4385,
   "stem": 3,
   "energy": 63.7471
  },
  {
   "t": 62.5081,
   "stem": 3,
   "energy": 65.1205
  },
  {
   "t": 62.7635,
   "stem": 3,
   "energy": 25.203
  },
  {
   "t": 63.0654,
   "stem": 3,
   "energy": 70.4629
  },
  {
   "t": 63.4137,
   "stem": 0,
   "energy": 0.4376
  },
  {
   "t": 63.5066,
   "stem": 3,
   "energy": 19.7818
  },
  {
   "t": 63.553,
   "stem": 0,
   "energy": 4.0635
  },
  {
   "t": 63.762,
   "stem": 3,
   "energy": 23.274
  },
  {
   "t": 63.8084,
   "stem": 0,
   "energy": 3.9005
  },
  {
   "t": 64.0174,
   "stem": 3,
   "energy": 20.6514
  },
  {
   "t": 64.4122,
   "stem": 3,
   "energy": 0.9665
  },
  {
   "t": 64.5283,
   "stem": 0,
   "energy": 0.0025
  },
  {
   "t": 64.7372,
   "stem": 1,
   "energy": 0.0095
  },
  {
   "t": 64.7837,
   "stem": 3,
   "energy": 2.1139
  },
  {
   "t": 64.8766,
   "stem": 6,
   "energy": 0.0021
  },
  {
   "t": 65.0159,
   "stem": 3,
   "energy": 0.3894
  },
  {
   "t": 65.1552,
   "stem": 3,
   "energy": 57.3462
  },
  {
   "t": 65.3177,
   "stem": 6,
   "energy": 0.0047
  },
  {
   "t": 65.4338,
   "stem": 3,
   "energy": 8.0651
  },
  {
   "t": 65.5267,
   "stem": 3,
   "energy": 15.83
  },
  {
   "t": 65.8054,
   "stem": 3,
   "energy": 38.5324
  },
  {
   "t": 65.875,
   "stem": 6,
   "energy": 0.0017
  },
  {
   "t": 66.0376,
   "stem": 0,
   "energy": 7.4529
  },
  {
   "t": 66.1304,
   "stem": 6,
   "energy": 0.0007
  },
  {
   "t": 66.293,
   "stem": 0,
   "energy": 0.0038
  },
  {
   "t": 66.4323,
   "stem": 1,
   "energy": 5.7313
  },
  {
   "t": 66.5252,
   "stem": 3,
   "energy": 13.4438
  },
  {
   "t": 66.7574,
   "stem": 3,
   "energy": 0.0854
  },
  {
   "t": 66.8038,
   "stem": 0,
   "energy": 31.4537
  },
  {
   "t": 66.9199,
   "stem": 6,
   "energy": 0.001
  },
  {
   "t": 67.036,
   "stem": 3,
   "energy": 5.6811
  },
  {
   "t": 67.1753,
   "stem": 3,
   "energy": 33.1261
  },
  {
   "t": 67.2682,
   "stem": 6,
   "energy": 0.0018
  },
  {
   "t": 67.3843,
   "stem": 3,
   "energy": 0.4717
  },
  {
   "t": 67.4307,
   "stem": 1,
   "energy": 4.7744
  },
  {
   "t": 67.5236,
   "stem": 3,
   "energy": 11.4708
  },
  {
   "t": 67.5701,
   "stem": 6,
   "energy": 0.0164
  },
  {
   "t": 67.6629,
   "stem": 6,
   "energy": 0.041
  },
  {
   "t": 67.8023,
   "stem": 1,
   "energy": 7.256
  },
  {
   "t": 67.9184,
   "stem": 3,
   "energy": 12.6445
  },
  {
   "t": 68.0112,
   "stem": 0,
   "energy": 0.0001
  },
  {
   "t": 68.0577,
   "stem": 3,
   "energy": 52.4378
  },
  {
   "t": 68.1273,
   "stem": 6,
   "energy": 0.009
  },
  {
   "t": 68.3363,
   "stem": 1,
   "energy": 0.0488
  },
  {
   "t": 68.3828,
   "stem": 3,
   "energy": 0.0324
  },
  {
   "t": 68.5453,
   "stem": 3,
   "energy": 13.6049
  },
  {
   "t": 68.6846,
   "stem": 6,
   "energy": 0.0059
  },
  {
   "t": 68.7543,
   "stem": 1,
   "energy": 0.0068
  },
  {
   "t": 68.8007,
   "stem": 3,
   "energy": 32.4344
  },
  {
   "t": 68.8936,
   "stem": 6,
   "energy": 0.002
  },
  {
   "t": 69.0561,
   "stem": 3,
   "energy": 39.5634
  },
  {
   "t": 69.1258,
   "stem": 6,
   "energy": 0.0026
  },
  {
   "t": 69.1722,
   "stem": 3,
   "energy": 41.8067
  },
  {
   "t": 69.2651,
   "stem": 6,
   "energy": 0.0034
  },
  {
   "t": 69.4277,
   "stem": 1,
   "energy": 8.8069
  },
  {
   "t": 69.4973,
   "stem": 0,
   "energy": 0.0005
  },
  {
   "t": 69.5438,
   "stem": 3,
   "energy": 15.6027
  },
  {
   "t": 69.7295,
   "stem": 1,
   "energy": 0.007
  },
  {
   "t": 69.7992,
   "stem": 3,
   "energy": 28.9967
  },
  {
   "t": 69.8921,
   "stem": 6,
   "energy": 0.0107
  },
  {
   "t": 70.0314,
   "stem": 3,
   "energy": 2.5806
  },
  {
   "t": 70.1707,
   "stem": 6,
   "energy": 0.0026
  },
  {
   "t": 70.31,
   "stem": 6,
   "energy": 0.0053
  },
  {
   "t": 70.4261,
   "stem": 3,
   "energy": 28.2538
  },
  {
   "t": 70.6583,
   "stem": 6,
   "energy": 0.0067
  },
  {
   "t": 70.7512,
   "stem": 1,
   "energy": 0.0026
  },
  {
   "t": 70.7976,
   "stem": 3,
   "energy": 31.3672
  },
  {
   "t": 71.0531,
   "stem": 3,
   "energy": 34.2008
  },
  {
   "t": 71.1692,
   "stem": 3,
   "energy": 32.6554
  },
  {
   "t": 71.4246,
   "stem": 1,
   "energy": 2.9707
  },
  {
   "t": 71.5175,
   "stem": 3,
   "energy": 12.0997
  },
  {
   "t": 71.7961,
   "stem": 3,
   "energy": 2.8146
  },
  {
   "t": 71.9122,
   "stem": 6,
   "energy": 0.0241
  },
  {
   "t": 72.0283,
   "stem": 3,
   "energy": 0.1924
  },
  {
   "t": 72.2605,
   "stem": 6,
   "energy": 0.9292
  },
  {
   "t": 72.3998,
   "stem": 3,
   "energy": 1.2303
  },
  {
   "t": 72.5159,
   "stem": 3,
   "energy": 17.2178
  },
  {
   "t": 72.6785,
   "stem": 0,
   "energy": 0.0244
  },
  {
   "t": 72.7946,
   "stem": 3,
   "energy": 36.2836
  },
  {
   "t": 73.05,
   "stem": 3,
   "energy": 27.0847
  },
  {
   "t": 73.1429,
   "stem": 1,
   "energy": 0.026
  },
  {
   "t": 73.1893,
   "stem": 3,
   "energy": 29.0161
  },
  {
   "t": 73.2822,
   "stem": 3,
   "energy": 14.6498
  },
  {
   "t": 73.3286,
   "stem": 6,
   "energy": 2.7453
  },
  {
   "t": 73.3983,
   "stem": 3,
   "energy": 2.1582
  },
  {
   "t": 73.4447,
   "stem": 6,
   "energy": 2.2445
  },
  {
   "t": 73.5144,
   "stem": 3,
   "energy": 18.7032
  },
  {
   "t": 73.5608,
   "stem": 6,
   "energy": 1.6165
  },
  {
   "t": 73.793,
   "stem": 3,
   "energy": 25.3481
  },
  {
   "t": 74.0484,
   "stem": 3,
   "energy": 31.9068
  },
  {
   "t": 74.2806,
   "stem": 3,
   "energy": 2.7113
  },
  {
   "t": 74.3967,
   "stem": 3,
   "energy": 1.1016
  },
  {
   "t": 74.5128,
   "stem": 3,
   "energy": 10.8904
  },
  {
   "t": 74.5593,
   "stem": 6,
   "energy": 0.8041
  },
  {
   "t": 74.7915,
   "stem": 3,
   "energy": 21.506
  },
  {
   "t": 75.0469,
   "stem": 3,
   "energy": 26.2598
  },
  {
   "t": 75.1398,
   "stem": 3,
   "energy": 76.4128
  },
  {
   "t": 75.1862,
   "stem": 0,
   "energy": 17.8908
  },
  {
   "t": 75.2791,
   "stem": 3,
   "energy": 24.5298
  },
  {
   "t": 75.4184,
   "stem": 3,
   "energy": 10.0756
  },
  {
   "t": 75.5113,
   "stem": 3,
   "energy": 25.8021
  },
  {
   "t": 75.7899,
   "stem": 3,
   "energy": 3.2766
  },
  {
   "t": 75.9525,
   "stem": 6,
   "energy": 1.7639
  },
  {
   "t": 76.0454,
   "stem": 0,
   "energy": 23.0496
  },
  {
   "t": 76.2543,
   "stem": 6,
   "energy": 0.5124
  },
  {
   "t": 76.4169,
   "stem": 3,
   "energy": 2.8773
  },
  {
   "t": 76.533,
   "stem": 3,
   "energy": 13.6484
  },
  {
   "t": 76.6955,
   "stem": 6,
   "energy": 0.5007
  },
  {
   "t": 76.7884,
   "stem": 3,
   "energy": 11.5383
  },
  {
   "t": 76.9277,
   "stem": 6,
   "energy": 0.2516
  },
  {
   "t": 77.0438,
   "stem": 3,
   "energy": 21.821
  },
  {
   "t": 77.1599,
   "stem": 3,
   "energy": 46.3545
  },
  {
   "t": 77.276,
   "stem": 6,
   "energy": 0.3271
  },
  {
   "t": 77.4153,
   "stem": 3,
   "energy": 1.6074
  },
  {
   "t": 77.5314,
   "stem": 3,
   "energy": 16.6634
  },
  {
   "t": 77.7868,
   "stem": 0,
   "energy": 6.8733
  },
  {
   "t": 78.0423,
   "stem": 0,
   "energy": 17.1594
  },
  {
   "t": 78.2512,
   "stem": 0,
   "energy": 0.0649
  },
  {
   "t": 78.437,
   "stem": 3,
   "energy": 8.4971
  },
  {
   "t": 78.5531,
   "stem": 6,
   "energy": 0.1334
  },
  {
   "t": 78.7389,
   "stem": 1,
   "energy": 0.0096
  },
  {
   "t": 78.7853,
   "stem": 3,
   "energy": 2.9609
  },
  {
   "t": 79.0407,
   "stem": 0,
   "energy": 12.9206
  },
  {
   "t": 79.18,
   "stem": 3,
   "energy": 24.5288
  },
  {
   "t": 79.2729,
   "stem": 6,
   "energy": 0.1893
  },
  {
   "t": 79.389,
   "stem": 1,
   "energy": 0.2037
  },
  {
   "t": 79.4355,
   "stem": 3,
   "energy": 8.9278
  },
  {
   "t": 79.5283,
   "stem": 3,
   "energy": 11.5876
  },
  {
   "t": 79.807,
   "stem": 1,
   "energy": 7.4073
  },
  {
   "t": 79.9231,
   "stem": 6,
   "energy": 0.6877
  },
  {
   "t": 80.0392,
   "stem": 3,
   "energy": 15.1932
  },
  {
   "t": 80.4339,
   "stem": 3,
   "energy": 16.3485
  },
  {
   "t": 80.5036,
   "stem": 6,
   "energy": 0.0815
  },
  {
   "t": 80.7358,
   "stem": 1,
   "energy": 0.0014
  },
  {
   "t": 80.8054,
   "stem": 3,
   "energy": 39.4584
  },
  {
   "t": 81.0376,
   "stem": 3,
   "energy": 8.7166
  },
  {
   "t": 81.1537,
   "stem": 3,
   "energy": 54.2006
  },
  {
   "t": 81.2698,
   "stem": 6,
   "energy": 0.5398
  },
  {
   "t": 81.4324,
   "stem": 3,
   "energy": 9.1037
  },
  {
   "t": 81.5253,
   "stem": 3,
   "energy": 15.6129
  },
  {
   "t": 81.8039,
   "stem": 3,
   "energy": 37.164
  },
  {
   "t": 82.0593,
   "stem": 3,
   "energy": 54.9402
  },
  {
   "t": 82.3844,
   "stem": 3,
   "energy": 0.2965
  },
  {
   "t": 82.5469,
   "stem": 6,
   "energy": 0.333
  },
  {
   "t": 82.6398,
   "stem": 6,
   "energy": 0.6442
  },
  {
   "t": 82.7327,
   "stem": 0,
   "energy": 0.0293
  },
  {
   "t": 82.8024,
   "stem": 3,
   "energy": 58.0342
  },
  {
   "t": 83.0346,
   "stem": 0,
   "energy": 3.7043
  },
  {
   "t": 83.1507,
   "stem": 3,
   "energy": 58.1917
  },
  {
   "t": 83.2668,
   "stem": 6,
   "energy": 0.1043
  },
  {
   "t": 83.3829,
   "stem": 1,
   "energy": 0.1564
  },
  {
   "t": 83.4293,
   "stem": 3,
   "energy": 5.6227
  },
  {
   "t": 83.5454,
   "stem": 3,
   "energy": 21.9828
  },
  {
   "t": 83.8008,
   "stem": 3,
   "energy": 7.0133
  },
  {
   "t": 83.8705,
   "stem": 6,
   "energy": 0.4371
  },
  {
   "t": 84.0562,
   "stem": 3,
   "energy": 38.9422
  },
  {
   "t": 84.3349,
   "stem": 6,
   "energy": 1.4693
  },
  {
   "t": 84.4278,
   "stem": 3,
   "energy": 11.3008
  },
  {
   "t": 84.5439,
   "stem": 3,
   "energy": 14.5323
  },
  {
   "t": 84.66,
   "stem": 6,
   "energy": 1.4934
  },
  {
   "t": 84.7761,
   "stem": 3,
   "energy": 0.94
  },
  {
   "t": 84.8225,
   "stem": 5,
   "energy": 0.0
  },
  {
   "t": 85.0083,
   "stem": 0,
   "energy": 0.0067
  },
  {
   "t": 85.0547,
   "stem": 3,
   "energy": 32.8581
  },
  {
   "t": 85.1476,
   "stem": 3,
   "energy": 62.9138
  },
  {
   "t": 85.2637,
   "stem": 6,
   "energy": 0.4104
  },
  {
   "t": 85.403,
   "stem": 3,
   "energy": 2.5811
  },
  {
   "t": 85.5423,
   "stem": 3,
   "energy": 15.1652
  },
  {
   "t": 85.7977,
   "stem": 1,
   "energy": 6.3804
  },
  {
   "t": 85.8906,
   "stem": 6,
   "energy": 0.262
  },
  {
   "t": 86.0067,
   "stem": 3,
   "energy": 1.5865
  },
  {
   "t": 86.1228,
   "stem": 6,
   "energy": 0.5139
  },
  {
   "t": 86.4247,
   "stem": 3,
   "energy": 10.4883
  },
  {
   "t": 86.564,
   "stem": 6,
   "energy": 0.4699
  },
  {
   "t": 86.7265,
   "stem": 1,
   "energy": 0.0033
  },
  {
   "t": 86.7962,
   "stem": 3,
   "energy": 8.1324
  },
  {
   "t": 86.8426,
   "stem": 6,
   "energy": 2.0974
  },
  {
   "t": 87.0748,
   "stem": 3,
   "energy": 8.5386
  },
  {
   "t": 87.1677,
   "stem": 3,
   "energy": 8.1241
  },
  {
   "t": 87.3767,
   "stem": 0,
   "energy": 1.1775
  },
  {
   "t": 87.4231,
   "stem": 1,
   "energy": 0.3368
  },
  {
   "t": 87.5392,
   "stem": 3,
   "energy": 7.2908
  },
  {
   "t": 87.7482,
   "stem": 0,
   "energy": 2.3816
  },
  {
   "t": 87.8179,
   "stem": 3,
   "energy": 12.1937
  },
  {
   "t": 88.0036,
   "stem": 1,
   "energy": 0.6939
  },
  {
   "t": 88.0501,
   "stem": 3,
   "energy": 38.7947
  },
  {
   "t": 88.4216,
   "stem": 3,
   "energy": 75.5795
  },
  {
   "t": 88.5145,
   "stem": 3,
   "energy": 54.601
  },
  {
   "t": 88.6073,
   "stem": 5,
   "energy": 0.0007
  },
  {
   "t": 88.8163,
   "stem": 3,
   "energy": 76.4316
  },
  {
   "t": 88.9092,
   "stem": 5,
   "energy": 0.0039
  },
  {
   "t": 89.0253,
   "stem": 3,
   "energy": 26.0562
  },
  {
   "t": 89.42,
   "stem": 0,
   "energy": 0.6285
  },
  {
   "t": 89.5361,
   "stem": 3,
   "energy": 19.6812
  },
  {
   "t": 89.7916,
   "stem": 3,
   "energy": 33.879
  },
  {
   "t": 90.0238,
   "stem": 3,
   "energy": 27.9321
  },
  {
   "t": 90.1166,
   "stem": 5,
   "energy": 0.0048
  },
  {
   "t": 90.2792,
   "stem": 0,
   "energy": 0.5922
  },
  {
   "t": 90.4185,
   "stem": 3,
   "energy": 26.211
  },
  {
   "t": 90.5114,
   "stem": 3,
   "energy": 18.0349
  },
  {
   "t": 90.6043,
   "stem": 5,
   "energy": 0.0079
  },
  {
   "t": 90.7436,
   "stem": 0,
   "energy": 0.0324
  },
  {
   "t": 90.79,
   "stem": 3,
   "energy": 20.1155
  },
  {
   "t": 90.999,
   "stem": 0,
   "energy": 0.0629
  },
  {
   "t": 91.0454,
   "stem": 3,
   "energy": 23.4083
  },
  {
   "t": 91.417,
   "stem": 3,
   "energy": 21.3914
  },
  {
   "t": 91.4634,
   "stem": 5,
   "energy": 0.101
  },
  {
   "t": 91.5563,
   "stem": 3,
   "energy": 26.3758
  },
  {
   "t": 91.7653,
   "stem": 3,
   "energy": 24.3697
  },
  {
   "t": 92.0439,
   "stem": 3,
   "energy": 38.2002
  },
  {
   "t": 92.1136,
   "stem": 6,
   "energy": 1.7536
  },
  {
   "t": 92.2761,
   "stem": 0,
   "energy": 0.5889
  },
  {
   "t": 92.4386,
   "stem": 3,
   "energy": 69.7609
  },
  {
   "t": 92.5083,
   "stem": 3,
   "energy": 108.5015
  },
  {
   "t": 92.7869,
   "stem": 3,
   "energy": 34.4278
  },
  {
   "t": 92.8798,
   "stem": 6,
   "energy": 2.4633
  },
  {
   "t": 93.0424,
   "stem": 3,
   "energy": 28.4695
  },
  {
   "t": 93.4139,
   "stem": 0,
   "energy": 0.1385
  },
  {
   "t": 93.53,
   "stem": 3,
   "energy": 19.5617
  },
  {
   "t": 93.7622,
   "stem": 3,
   "energy": 18.8584
  },
  {
   "t": 93.8318,
   "stem": 6,
   "energy": 1.2157
  },
  {
   "t": 94.0176,
   "stem": 3,
   "energy": 23.5979
  },
  {
   "t": 94.1105,
   "stem": 5,
   "energy": 0.0087
  },
  {
   "t": 94.273,
   "stem": 0,
   "energy": 0.1591
  },
  {
   "t": 94.3195,
   "stem": 6,
   "energy": 1.8291
  },
  {
   "t": 94.4123,
   "stem": 3,
   "energy": 26.3433
  },
  {
   "t": 94.5052,
   "stem": 3,
   "energy": 67.1629
  },
  {
   "t": 94.5517,
   "stem": 0,
   "energy": 22.3245
  },
  {
   "t": 94.6213,
   "stem": 5,
   "energy": 0.0395
  },
  {
   "t": 94.7606,
   "stem": 3,
   "energy": 10.2447
  },
  {
   "t": 95.0393,
   "stem": 3,
   "energy": 31.4301
  },
  {
   "t": 95.3876,
   "stem": 5,
   "energy": 0.1898
  },
  {
   "t": 95.5269,
   "stem": 3,
   "energy": 15.4041
  },
  {
   "t": 95.7823,
   "stem": 3,
   "energy": 35.301
  },
  {
   "t": 96.061,
   "stem": 3,
   "energy": 51.4939
  },
  {
   "t": 96.3396,
   "stem": 3,
   "energy": 20.6045
  },
  {
   "t": 96.386,
   "stem": 0,
   "energy": 0.0111
  },
  {
   "t": 96.5254,
   "stem": 3,
   "energy": 39.2981
  },
  {
   "t": 96.7808,
   "stem": 3,
   "energy": 20.0586
  },
  {
   "t": 97.0594,
   "stem": 3,
   "energy": 36.0186
  },
  {
   "t": 97.4077,
   "stem": 0,
   "energy": 0.0907
  },
  {
   "t": 97.5238,
   "stem": 3,
   "energy": 25.6046
  },
  {
   "t": 97.6399,
   "stem": 6,
   "energy": 2.9805
  },
  {
   "t": 97.7792,
   "stem": 3,
   "energy": 26.607
  },
  {
   "t": 98.0579,
   "stem": 3,
   "energy": 41.5444
  },
  {
   "t": 98.1275,
   "stem": 6,
   "energy": 2.446
  },
  {
   "t": 98.2901,
   "stem": 0,
   "energy": 0.1132
  },
  {
   "t": 98.4062,
   "stem": 3,
   "energy": 24.838
  },
  {
   "t": 98.5223,
   "stem": 3,
   "energy": 70.1384
  },
  {
   "t": 98.7777,
   "stem": 3,
   "energy": 20.1231
  },
  {
   "t": 99.0331,
   "stem": 3,
   "energy": 28.0331
  },
  {
   "t": 99.1724,
   "stem": 6,
   "energy": 2.9209
  },
  {
   "t": 99.4278,
   "stem": 0,
   "energy": 0.1126
  },
  {
   "t": 99.5207,
   "stem": 3,
   "energy": 15.5771
  },
  {
   "t": 99.7529,
   "stem": 3,
   "energy": 15.8129
  },
  {
   "t": 99.7994,
   "stem": 0,
   "energy": 0.4615
  },
  {
   "t": 100.0548,
   "stem": 3,
   "energy": 59.4215
  },
  {
   "t": 100.4031,
   "stem": 3,
   "energy": 21.6707
  },
  {
   "t": 100.5192,
   "stem": 3,
   "energy": 36.3876
  },
  {
   "t": 100.6585,
   "stem": 6,
   "energy": 1.3653
  },
  {
   "t": 100.7514,
   "stem": 3,
   "energy": 31.0335
  },
  {
   "t": 100.7978,
   "stem": 0,
   "energy": 18.1776
  },
  {
   "t": 101.03,
   "stem": 3,
   "energy": 16.4141
  },
  {
   "t": 101.1926,
   "stem": 6,
   "energy": 1.607
  },
  {
   "t": 101.2622,
   "stem": 0,
   "energy": 0.0469
  },
  {
   "t": 101.4015,
   "stem": 3,
   "energy": 18.9752
  },
  {
   "t": 101.5176,
   "stem": 3,
   "energy": 26.372
  },
  {
   "t": 101.7731,
   "stem": 3,
   "energy": 21.3004
  },
  {
   "t": 101.8892,
   "stem": 6,
   "energy": 0.6523
  },
  {
   "t": 101.9356,
   "stem": 0,
   "energy": 8.9994
  },
  {
   "t": 102.0517,
   "stem": 3,
   "energy": 48.4301
  },
  {
   "t": 102.1214,
   "stem": 6,
   "energy": 0.6816
  },
  {
   "t": 102.2607,
   "stem": 0,
   "energy": 0.2787
  },
  {
   "t": 102.4232,
   "stem": 0,
   "energy": 16.1635
  },
  {
   "t": 102.5161,
   "stem": 3,
   "energy": 52.5055
  },
  {
   "t": 102.6322,
   "stem": 6,
   "energy": 0.76
  },
  {
   "t": 102.7715,
   "stem": 3,
   "energy": 11.6919
  },
  {
   "t": 103.0502,
   "stem": 3,
   "energy": 23.2775
  },
  {
   "t": 103.3985,
   "stem": 0,
   "energy": 0.1709
  },
  {
   "t": 103.5146,
   "stem": 3,
   "energy": 18.2295
  },
  {
   "t": 103.77,
   "stem": 3,
   "energy": 11.9235
  },
  {
   "t": 103.9093,
   "stem": 0,
   "energy": 0.1679
  },
  {
   "t": 104.0254,
   "stem": 3,
   "energy": 17.1094
  },
  {
   "t": 104.2112,
   "stem": 6,
   "energy": 0.747
  },
  {
   "t": 104.3969,
   "stem": 3,
   "energy": 22.515
  },
  {
   "t": 104.513,
   "stem": 3,
   "energy": 46.2622
  },
  {
   "t": 104.6523,
   "stem": 6,
   "energy": 0.9048
  },
  {
   "t": 104.7917,
   "stem": 3,
   "energy": 44.767
  },
  {
   "t": 105.0471,
   "stem": 3,
   "energy": 41.7707
  },
  {
   "t": 105.4186,
   "stem": 0,
   "energy": 0.1882
  },
  {
   "t": 105.5115,
   "stem": 3,
   "energy": 22.2969
  },
  {
   "t": 105.8133,
   "stem": 3,
   "energy": 61.0276
  },
  {
   "t": 106.0455,
   "stem": 3,
   "energy": 46.3752
  },
  {
   "t": 106.2777,
   "stem": 0,
   "energy": 1.0279
  },
  {
   "t": 106.4403,
   "stem": 0,
   "energy": 1.0411
  },
  {
   "t": 106.5332,
   "stem": 3,
   "energy": 22.1583
  },
  {
   "t": 106.7886,
   "stem": 3,
   "energy": 39.6464
  },
  {
   "t": 106.8815,
   "stem": 6,
   "energy": 2.9465
  },
  {
   "t": 107.044,
   "stem": 3,
   "energy": 38.9494
  },
  {
   "t": 107.2994,
   "stem": 5,
   "energy": 0.005
  },
  {
   "t": 107.3923,
   "stem": 0,
   "energy": 0.12
  },
  {
   "t": 107.5548,
   "stem": 3,
   "energy": 25.8145
  },
  {
   "t": 107.787,
   "stem": 0,
   "energy": 1.4151
  },
  {
   "t": 108.0192,
   "stem": 5,
   "energy": 0.0786
  },
  {
   "t": 108.8087,
   "stem": 3,
   "energy": 0.5258
  },
  {
   "t": 108.9712,
   "stem": 6,
   "energy": 0.0043
  },
  {
   "t": 109.0409,
   "stem": 3,
   "energy": 1.7623
  },
  {
   "t": 109.5517,
   "stem": 3,
   "energy": 1.7886
  },
  {
   "t": 109.6446,
   "stem": 6,
   "energy": 0.0169
  },
  {
   "t": 110.0626,
   "stem": 3,
   "energy": 1.7981
  },
  {
   "t": 110.2483,
   "stem": 6,
   "energy": 0.0005
  },
  {
   "t": 110.3412,
   "stem": 6,
   "energy": 0.0002
  },
  {
   "t": 110.4573,
   "stem": 3,
   "energy": 0.4213
  },
  {
   "t": 110.5038,
   "stem": 5,
   "energy": 0.1647
  },
  {
   "t": 110.6663,
   "stem": 5,
   "energy": 3.7751
  },
  {
   "t": 110.7824,
   "stem": 5,
   "energy": 2.1738
  },
  {
   "t": 111.0378,
   "stem": 3,
   "energy": 1.0314
  }
 ]
}